{
  "version": "1.0",
  "truncation": null,
  "padding": null,
  "added_tokens": [
    {
      "id": 0,
      "content": "[UNK]",
      "single_word": false,
      "lstrip": false,
      "rstrip": false,
      "normalized": false,
      "special": true
    },
    {
      "id": 1,
      "content": "[PAD]",
      "single_word": false,
      "lstrip": false,
      "rstrip": false,
      "normalized": false,
      "special": true
    },
    {
      "id": 2,
      "content": "[SOS]",
      "single_word": false,
      "lstrip": false,
      "rstrip": false,
      "normalized": false,
      "special": true
    },
    {
      "id": 3,
      "content": "[EOS]",
      "single_word": false,
      "lstrip": false,
      "rstrip": false,
      "normalized": false,
      "special": true
    }
  ],
  "normalizer": null,
  "pre_tokenizer": {
    "type": "Whitespace"
  },
  "post_processor": null,
  "decoder": null,
  "model": {
    "type": "WordLevel",
    "vocab": {
      "[UNK]": 0,
      "[PAD]": 1,
      "[SOS]": 2,
      "[EOS]": 3,
      "tôi": 4,
      ".": 5,
      "bạn": 6,
      "không": 7,
      "có": 8,
      "tom": 9,
      "một": 10,
      "đã": 11,
      "của": 12,
      "anh": 13,
      "là": 14,
      "?": 15,
      "ấy": 16,
      "chúng": 17,
      "sẽ": 18,
      "thể": 19,
      "với": 20,
      "làm": 21,
      "đó": 22,
      "gì": 23,
      "nói": 24,
      "cho": 25,
      ",": 26,
      "Tom": 27,
      "ta": 28,
      "Tôi": 29,
      "ở": 30,
      "đến": 31,
      "muốn": 32,
      "đi": 33,
      "cô": 34,
      "này": 35,
      "trong": 36,
      "để": 37,
      "đang": 38,
      "phải": 39,
      "người": 40,
      "điều": 41,
      "biết": 42,
      "nó": 43,
      "mary": 44,
      "những": 45,
      "được": 46,
      "về": 47,
      "và": 48,
      "vào": 49,
      "ra": 50,
      "khi": 51,
      "rằng": 52,
      "rất": 53,
      "giờ": 54,
      "nghĩ": 55,
      "thấy": 56,
      "đây": 57,
      "mình": 58,
      "họ": 59,
      "như": 60,
      "nhà": 61,
      "sự": 62,
      "bị": 63,
      "việc": 64,
      "nào": 65,
      "nhiều": 66,
      "thích": 67,
      "lại": 68,
      "ngày": 69,
      "cả": 70,
      "hơn": 71,
      "tốt": 72,
      "nên": 73,
      "bao": 74,
      "ăn": 75,
      "cần": 76,
      "từ": 77,
      "chỉ": 78,
      "ai": 79,
      "con": 80,
      "học": 81,
      "cái": 82,
      "công": 83,
      "xe": 84,
      "ông": 85,
      "trên": 86,
      "tiếng": 87,
      "qua": 88,
      "thế": 89,
      "sao": 90,
      "thực": 91,
      "chuyện": 92,
      "trước": 93,
      "đề": 94,
      "thời": 95,
      "Anh": 96,
      "đầu": 97,
      "giúp": 98,
      "mọi": 99,
      "thứ": 100,
      "thành": 101,
      "hỏi": 102,
      "tất": 103,
      "bất": 104,
      "các": 105,
      "gặp": 106,
      "nếu": 107,
      "tại": 108,
      "vì": 109,
      "cảm": 110,
      "sống": 111,
      "thật": 112,
      "tin": 113,
      "năm": 114,
      "bắt": 115,
      "nhìn": 116,
      "nay": 117,
      "yêu": 118,
      "chưa": 119,
      "nhất": 120,
      "tiền": 121,
      "gian": 122,
      "xảy": 123,
      "ý": 124,
      "số": 125,
      "nghe": 126,
      "vui": 127,
      "tìm": 128,
      "khác": 129,
      "đừng": 130,
      "hôm": 131,
      "nhận": 132,
      "cuộc": 133,
      "vấn": 134,
      "chiếc": 135,
      "trở": 136,
      "hai": 137,
      "phòng": 138,
      "lên": 139,
      "quá": 140,
      "chơi": 141,
      "cách": 142,
      "viên": 143,
      "tự": 144,
      "mua": 145,
      "câu": 146,
      "Bạn": 147,
      "lời": 148,
      "sách": 149,
      "nhưng": 150,
      "sau": 151,
      "bằng": 152,
      "cùng": 153,
      "cứ": 154,
      "hàng": 155,
      "quan": 156,
      "đâu": 157,
      "tối": 158,
      "ba": 159,
      "xem": 160,
      "chắc": 161,
      "nhau": 162,
      "cửa": 163,
      "lớn": 164,
      "xin": 165,
      "định": 166,
      "vậy": 167,
      "lúc": 168,
      "lần": 169,
      "nữa": 170,
      "bây": 171,
      "cố": 172,
      "mà": 173,
      "gọi": 174,
      "mới": 175,
      "còn": 176,
      "lòng": 177,
      "khỏi": 178,
      "theo": 179,
      "ngoài": 180,
      "sinh": 181,
      "thường": 182,
      "nước": 183,
      "trẻ": 184,
      "ngủ": 185,
      "trả": 186,
      "hãy": 187,
      "cầu": 188,
      "luôn": 189,
      "tay": 190,
      "ngay": 191,
      "hoàn": 192,
      "gia": 193,
      "boston": 194,
      "đưa": 195,
      "mất": 196,
      "đường": 197,
      "kết": 198,
      "bài": 199,
      "bỏ": 200,
      "cuốn": 201,
      "khó": 202,
      "vẻ": 203,
      "trường": 204,
      "rời": 205,
      "bộ": 206,
      "gái": 207,
      "bữa": 208,
      "quyết": 209,
      "đợi": 210,
      "chắn": 211,
      "Cô": 212,
      "hiểu": 213,
      "lỗi": 214,
      "máy": 215,
      "vẫn": 216,
      "mẹ": 217,
      "lý": 218,
      "sáng": 219,
      "Pháp": 220,
      "trai": 221,
      "lấy": 222,
      "gắng": 223,
      "sớm": 224,
      "tâm": 225,
      "hiện": 226,
      "động": 227,
      "nơi": 228,
      "vọng": 229,
      "đồng": 230,
      "kỳ": 231,
      "đọc": 232,
      "đàn": 233,
      "cuối": 234,
      "tuần": 235,
      "đánh": 236,
      "uống": 237,
      "trời": 238,
      "toàn": 239,
      "chính": 240,
      "đẹp": 241,
      "mai": 242,
      "Có": 243,
      "thức": 244,
      "thư": 245,
      "chết": 246,
      "đúng": 247,
      "đặt": 248,
      "hôn": 249,
      "giải": 250,
      "đều": 251,
      "mặt": 252,
      "gần": 253,
      "vài": 254,
      "giá": 255,
      "giữ": 256,
      "dụng": 257,
      "cũng": 258,
      "sai": 259,
      "bảo": 260,
      "lắng": 261,
      "ngồi": 262,
      "tưởng": 263,
      "viết": 264,
      "mỗi": 265,
      "áo": 266,
      "\"": 267,
      "đỡ": 268,
      "xuống": 269,
      "nhớ": 270,
      "em": 271,
      "cha": 272,
      "tức": 273,
      "giáo": 274,
      "Tại": 275,
      "tên": 276,
      "cây": 277,
      "trông": 278,
      "thông": 279,
      "báo": 280,
      "đủ": 281,
      "sĩ": 282,
      "trọng": 283,
      "chút": 284,
      "cao": 285,
      "lâu": 286,
      "sợ": 287,
      "đêm": 288,
      "bé": 289,
      "hợp": 290,
      "sử": 291,
      "ít": 292,
      "nhân": 293,
      "hành": 294,
      "điện": 295,
      "tuổi": 296,
      "tập": 297,
      "chó": 298,
      "nhiêu": 299,
      "thay": 300,
      "tiếp": 301,
      "nhanh": 302,
      "bên": 303,
      "ảnh": 304,
      "lo": 305,
      "kế": 306,
      "chạy": 307,
      "hy": 308,
      "tuyệt": 309,
      "ơn": 310,
      "nghỉ": 311,
      "bận": 312,
      "dự": 313,
      "cảnh": 314,
      "mặc": 315,
      "khá": 316,
      "bản": 317,
      "tháng": 318,
      "tàu": 319,
      "Nhật": 320,
      "đối": 321,
      "vụ": 322,
      "hết": 323,
      "nhiên": 324,
      "tình": 325,
      "do": 326,
      "bay": 327,
      "chăm": 328,
      "hay": 329,
      "chiến": 330,
      "phát": 331,
      "mở": 332,
      "hoạch": 333,
      "mưa": 334,
      "mang": 335,
      "từng": 336,
      "cơ": 337,
      "chủ": 338,
      "vị": 339,
      "bệnh": 340,
      "hạnh": 341,
      "thuốc": 342,
      "đồ": 343,
      "cười": 344,
      "bàn": 345,
      "hội": 346,
      "sát": 347,
      "giới": 348,
      "phúc": 349,
      "đổi": 350,
      "phụ": 351,
      "tiệc": 352,
      "đáng": 353,
      "dễ": 354,
      "thương": 355,
      "mười": 356,
      "bóng": 357,
      "bánh": 358,
      "nhạc": 359,
      "lẽ": 360,
      "tranh": 361,
      "năng": 362,
      "đôi": 363,
      "bơi": 364,
      "hình": 365,
      "lái": 366,
      "dài": 367,
      "nhỏ": 368,
      "ngôi": 369,
      "lạnh": 370,
      "đơn": 371,
      "đại": 372,
      "buổi": 373,
      "cà": 374,
      "màu": 375,
      "kiểm": 376,
      "mong": 377,
      "khách": 378,
      "bố": 379,
      "hát": 380,
      "rồi": 381,
      "tai": 382,
      "tham": 383,
      "ước": 384,
      "quên": 385,
      "cá": 386,
      "tra": 387,
      "!": 388,
      "phút": 389,
      "nghị": 390,
      "thú": 391,
      "khăn": 392,
      "trung": 393,
      "vừa": 394,
      "tiết": 395,
      "mắt": 396,
      "chuyến": 397,
      "giống": 398,
      "lập": 399,
      "tới": 400,
      "đứa": 401,
      "chờ": 402,
      "dường": 403,
      "nhật": 404,
      "hơi": 405,
      "thoại": 406,
      "thêm": 407,
      "tiên": 408,
      "kinh": 409,
      "thị": 410,
      "đau": 411,
      "nữ": 412,
      "quả": 413,
      "Làm": 414,
      "nạn": 415,
      "sức": 416,
      "kiếm": 417,
      "chọn": 418,
      "bình": 419,
      "lịch": 420,
      "sẵn": 421,
      "phố": 422,
      "Bản": 423,
      "điểm": 424,
      "văn": 425,
      "bức": 426,
      "dành": 427,
      "loại": 428,
      "mùa": 429,
      "thất": 430,
      "nghĩa": 431,
      "đứng": 432,
      "hồ": 433,
      "quanh": 434,
      "phục": 435,
      "thân": 436,
      "chuyển": 437,
      "dậy": 438,
      "xấu": 439,
      "bởi": 440,
      "kể": 441,
      "mươi": 442,
      "đình": 443,
      "xuất": 444,
      "xa": 445,
      "Hãy": 446,
      "chứ": 447,
      "chí": 448,
      "khóa": 449,
      "thăm": 450,
      "lớp": 451,
      "biệt": 452,
      "la": 453,
      "chú": 454,
      "quay": 455,
      "tính": 456,
      "chịu": 457,
      "giết": 458,
      "trò": 459,
      "cấp": 460,
      "giận": 461,
      "vời": 462,
      "dối": 463,
      "Khi": 464,
      "duy": 465,
      "thuyết": 466,
      "họp": 467,
      "Điều": 468,
      "đóng": 469,
      "cẩn": 470,
      "sàng": 471,
      "thử": 472,
      "phép": 473,
      "phí": 474,
      "phim": 475,
      "rõ": 476,
      "trí": 477,
      "ngốc": 478,
      "bán": 479,
      "phê": 480,
      "rối": 481,
      "khuyên": 482,
      "trưa": 483,
      "ngạc": 484,
      "hiểm": 485,
      "phía": 486,
      "quần": 487,
      "đất": 488,
      "giỏi": 489,
      "minh": 490,
      "gửi": 491,
      "muộn": 492,
      "liên": 493,
      "lầm": 494,
      "tài": 495,
      "tội": 496,
      "lạc": 497,
      "rượu": 498,
      "chân": 499,
      "buýt": 500,
      "tệ": 501,
      "xử": 502,
      "mệt": 503,
      "viện": 504,
      "hóa": 505,
      "hòa": 506,
      "xác": 507,
      "tục": 508,
      "luận": 509,
      "buồn": 510,
      "thận": 511,
      "bác": 512,
      "ổn": 513,
      "mạnh": 514,
      "kẻ": 515,
      ".\"": 516,
      "món": 517,
      "à": 518,
      "càng": 519,
      "phạm": 520,
      "trái": 521,
      "vô": 522,
      "đô": 523,
      "an": 524,
      "john": 525,
      "cậu": 526,
      "phần": 527,
      "ngữ": 528,
      "ty": 529,
      "hầu": 530,
      "tế": 531,
      "cứu": 532,
      "đội": 533,
      "dù": 534,
      "bước": 535,
      "trang": 536,
      "khả": 537,
      "cũ": 538,
      "giả": 539,
      "căn": 540,
      "dừng": 541,
      "mèo": 542,
      "khỏe": 543,
      "phiền": 544,
      "ngờ": 545,
      "túi": 546,
      "quen": 547,
      "suy": 548,
      "chấp": 549,
      "thúc": 550,
      "lá": 551,
      "hút": 552,
      "tuyết": 553,
      "vượt": 554,
      "chiều": 555,
      "ghét": 556,
      "dưới": 557,
      "nguy": 558,
      "sáu": 559,
      "thậm": 560,
      "tượng": 561,
      "nóng": 562,
      "vật": 563,
      "sóc": 564,
      "sổ": 565,
      "nổi": 566,
      "ga": 567,
      "đông": 568,
      "đổ": 569,
      "đá": 570,
      "hoa": 571,
      "rộn": 572,
      "nghi": 573,
      "lạ": 574,
      "ràng": 575,
      "thống": 576,
      "dàng": 577,
      "nhiệm": 578,
      "mật": 579,
      "Mỹ": 580,
      "âm": 581,
      "bí": 582,
      "hoặc": 583,
      "trấn": 584,
      "tăng": 585,
      "đói": 586,
      "cáo": 587,
      "khoảng": 588,
      "ký": 589,
      "thiết": 590,
      "kiến": 591,
      "ngu": 592,
      "vợ": 593,
      "đoán": 594,
      "may": 595,
      "kéo": 596,
      "du": 597,
      "thuộc": 598,
      "hứa": 599,
      "hài": 600,
      "tương": 601,
      "bè": 602,
      "quốc": 603,
      "luật": 604,
      "sửa": 605,
      "độ": 606,
      "bại": 607,
      "khóc": 608,
      "phá": 609,
      "già": 610,
      "đầy": 611,
      "giữa": 612,
      "cánh": 613,
      "mỏi": 614,
      "nhảy": 615,
      "diễn": 616,
      "thì": 617,
      "cắt": 618,
      "ngừng": 619,
      ":": 620,
      "băng": 621,
      "lặng": 622,
      "rơi": 623,
      "trị": 624,
      "dạy": 625,
      "ngoại": 626,
      "rắc": 627,
      "tóc": 628,
      "giày": 629,
      "chức": 630,
      "giao": 631,
      "sư": 632,
      "trình": 633,
      "nghiệp": 634,
      "di": 635,
      "hộp": 636,
      "ngăn": 637,
      "sắp": 638,
      "ly": 639,
      "lực": 640,
      "doanh": 641,
      "biển": 642,
      "thắng": 643,
      "giảm": 644,
      "khí": 645,
      "?\"": 646,
      "giường": 647,
      "ô": 648,
      "nằm": 649,
      "cơn": 650,
      "cạnh": 651,
      "dân": 652,
      "liệu": 653,
      "mơ": 654,
      "pháp": 655,
      "tồi": 656,
      "sở": 657,
      "buộc": 658,
      "cung": 659,
      "đạp": 660,
      "chi": 661,
      "lượng": 662,
      "mái": 663,
      "đám": 664,
      "riêng": 665,
      "chỗ": 666,
      "hộ": 667,
      "30": 668,
      "biến": 669,
      "ghế": 670,
      "cổ": 671,
      "mời": 672,
      "thi": 673,
      "hoạt": 674,
      "mượn": 675,
      "ốm": 676,
      "chàng": 677,
      "hè": 678,
      "tắt": 679,
      "đấu": 680,
      "chìa": 681,
      "thoát": 682,
      "bảy": 683,
      "đỏ": 684,
      "sông": 685,
      "nghiêm": 686,
      "điên": 687,
      "khiến": 688,
      "yên": 689,
      "im": 690,
      "dịch": 691,
      "hiệu": 692,
      "sạn": 693,
      "thanh": 694,
      "trách": 695,
      "xét": 696,
      "sân": 697,
      "lắm": 698,
      "quy": 699,
      "đời": 700,
      "Nếu": 701,
      "ban": 702,
      "dẫn": 703,
      "hướng": 704,
      "thu": 705,
      "vệ": 706,
      "đặc": 707,
      "chuẩn": 708,
      "giàu": 709,
      "lãng": 710,
      "tắm": 711,
      "hẹn": 712,
      "tránh": 713,
      "Người": 714,
      "chối": 715,
      "thảo": 716,
      "lựa": 717,
      "mức": 718,
      "táo": 719,
      "Ai": 720,
      "phản": 721,
      "thủ": 722,
      "ích": 723,
      "chứng": 724,
      "so": 725,
      "gây": 726,
      "phủ": 727,
      "trễ": 728,
      "Những": 729,
      "quà": 730,
      "ngon": 731,
      "Thật": 732,
      "mắn": 733,
      "nấu": 734,
      "bầu": 735,
      "thiếu": 736,
      "địa": 737,
      "xung": 738,
      "chằm": 739,
      "trượt": 740,
      "khoác": 741,
      "súng": 742,
      "tổn": 743,
      "biểu": 744,
      "tòa": 745,
      "tử": 746,
      "xanh": 747,
      "mũ": 748,
      "sản": 749,
      "chị": 750,
      "tiêu": 751,
      "xong": 752,
      "chia": 753,
      "vàng": 754,
      "tác": 755,
      "tù": 756,
      "váy": 757,
      "kính": 758,
      "giấy": 759,
      "tư": 760,
      "Con": 761,
      "trắng": 762,
      "án": 763,
      "Không": 764,
      "sang": 765,
      "xuyên": 766,
      "bốn": 767,
      "trận": 768,
      "hữu": 769,
      "khu": 770,
      "thuê": 771,
      "đảm": 772,
      "ngôn": 773,
      "thôi": 774,
      "vỡ": 775,
      "phẩm": 776,
      "trốn": 777,
      "nỗi": 778,
      "vũ": 779,
      "danh": 780,
      "núi": 781,
      "nửa": 782,
      "quyền": 783,
      "đèn": 784,
      "đùa": 785,
      "thịt": 786,
      "vé": 787,
      "cắp": 788,
      "ngoái": 789,
      "ngắn": 790,
      "hào": 791,
      "lỡ": 792,
      "thẳng": 793,
      "2": 794,
      "bắn": 795,
      "trợ": 796,
      "Một": 797,
      "lửa": 798,
      "ngân": 799,
      "thang": 800,
      "tạo": 801,
      "dọn": 802,
      "quản": 803,
      "coi": 804,
      "trưởng": 805,
      "bút": 806,
      "cân": 807,
      "đen": 808,
      "bếp": 809,
      "điển": 810,
      "khủng": 811,
      "kia": 812,
      "thuật": 813,
      "toán": 814,
      "xúc": 815,
      "tv": 816,
      "bật": 817,
      "cờ": 818,
      "hủy": 819,
      "nhập": 820,
      "nặng": 821,
      "dạo": 822,
      "niềm": 823,
      "Đức": 824,
      "say": 825,
      "tổ": 826,
      "Nó": 827,
      "tennis": 828,
      "thừa": 829,
      "bia": 830,
      "hổ": 831,
      "tắc": 832,
      "Ông": 833,
      "piano": 834,
      "vội": 835,
      "Trung": 836,
      "giác": 837,
      "kịp": 838,
      "mấy": 839,
      "sữa": 840,
      "chồng": 841,
      "hại": 842,
      "nhẫn": 843,
      "nợ": 844,
      "xây": 845,
      "chim": 846,
      "cháy": 847,
      "dục": 848,
      "rửa": 849,
      "Quốc": 850,
      "thuận": 851,
      "bà": 852,
      "thơ": 853,
      "ứng": 854,
      "ngựa": 855,
      "xinh": 856,
      "nghiệm": 857,
      "ngơi": 858,
      "chán": 859,
      "miễn": 860,
      "vòng": 861,
      "Đây": 862,
      "cư": 863,
      "mì": 864,
      "thiện": 865,
      "tiếc": 866,
      "trăm": 867,
      "chào": 868,
      "tiểu": 869,
      "dựng": 870,
      "đeo": 871,
      "độc": 872,
      "chậm": 873,
      "chống": 874,
      "ghi": 875,
      "giấu": 876,
      "áp": 877,
      "chóng": 878,
      "giấc": 879,
      "trà": 880,
      "tĩnh": 881,
      "mục": 882,
      "Đó": 883,
      "chung": 884,
      "ném": 885,
      "tờ": 886,
      "lương": 887,
      "phù": 888,
      "vườn": 889,
      "ồn": 890,
      "nàn": 891,
      "chày": 892,
      "hỏng": 893,
      "khoản": 894,
      "nhờ": 895,
      "phàn": 896,
      "tách": 897,
      "đón": 898,
      "nghệ": 899,
      "tường": 900,
      "vi": 901,
      "hệ": 902,
      "thuyền": 903,
      "tận": 904,
      "bão": 905,
      "tám": 906,
      "cưới": 907,
      "tạp": 908,
      "hạn": 909,
      "tiến": 910,
      "trừ": 911,
      "đạt": 912,
      "đắt": 913,
      "bãi": 914,
      "kỹ": 915,
      "nghèo": 916,
      "ấm": 917,
      "Chúng": 918,
      "khẩu": 919,
      "tây": 920,
      "đột": 921,
      "khoa": 922,
      "lừa": 923,
      "vẽ": 924,
      "hưởng": 925,
      "truyền": 926,
      "hét": 927,
      "lệ": 928,
      "ví": 929,
      "chữa": 930,
      "hiếm": 931,
      "lợi": 932,
      "trứng": 933,
      "lỗ": 934,
      "mừng": 935,
      "to": 936,
      "trộm": 937,
      "miệng": 938,
      "sâu": 939,
      "tinh": 940,
      "cập": 941,
      "dùng": 942,
      "tải": 943,
      "tặng": 944,
      "yếu": 945,
      "dây": 946,
      "nhẹ": 947,
      "tủ": 948,
      "giọng": 949,
      "tim": 950,
      "sắc": 951,
      "tôn": 952,
      "mắc": 953,
      "ngọn": 954,
      "sắm": 955,
      "suốt": 956,
      "ngã": 957,
      "ấn": 958,
      "ca": 959,
      "kiện": 960,
      "nhầm": 961,
      "phương": 962,
      "thỏa": 963,
      "bông": 964,
      "Họ": 965,
      "Tokyo": 966,
      "chế": 967,
      "kỷ": 968,
      "lưng": 969,
      "tha": 970,
      "chuyên": 971,
      "nhắn": 972,
      "trại": 973,
      "chất": 974,
      "chụp": 975,
      "lai": 976,
      "nhiệt": 977,
      "nhóm": 978,
      "quân": 979,
      "Bây": 980,
      "mãi": 981,
      "quán": 982,
      "ánh": 983,
      "phong": 984,
      "nắm": 985,
      "đậu": 986,
      "Sau": 987,
      "bụng": 988,
      "dòng": 989,
      "giành": 990,
      "kiên": 991,
      "dấu": 992,
      "hãi": 993,
      "chạm": 994,
      "dao": 995,
      "leo": 996,
      "tivi": 997,
      "cãi": 998,
      "guitar": 999,
      "nguyên": 1000,
      "rút": 1001,
      "tầng": 1002,
      "cặp": 1003,
      "hảo": 1004,
      "che": 1005,
      "hối": 1006,
      "môn": 1007,
      "trạng": 1008,
      "Cậu": 1009,
      "can": 1010,
      "kiệm": 1011,
      "sạch": 1012,
      "chai": 1013,
      "cực": 1014,
      "thao": 1015,
      "y": 1016,
      "bối": 1017,
      "chín": 1018,
      "cải": 1019,
      "răng": 1020,
      "sàn": 1021,
      "đựng": 1022,
      "ngón": 1023,
      "nuôi": 1024,
      "tích": 1025,
      "Các": 1026,
      "cử": 1027,
      "phiếu": 1028,
      "thờ": 1029,
      "trải": 1030,
      "10": 1031,
      "chương": 1032,
      "nướng": 1033,
      "thoảng": 1034,
      "thấp": 1035,
      "vờ": 1036,
      "ken": 1037,
      "khiếp": 1038,
      "vắng": 1039,
      "chữ": 1040,
      "gấp": 1041,
      "tỉnh": 1042,
      "vực": 1043,
      "dõi": 1044,
      "đằng": 1045,
      "hò": 1046,
      "thiệu": 1047,
      "chảy": 1048,
      "gió": 1049,
      "thần": 1050,
      "giản": 1051,
      "đạo": 1052,
      "chặt": 1053,
      "ghé": 1054,
      "khích": 1055,
      "taxi": 1056,
      "đẩy": 1057,
      "châu": 1058,
      "thù": 1059,
      "thở": 1060,
      "khắc": 1061,
      "thiên": 1062,
      "thô": 1063,
      "chúc": 1064,
      "paris": 1065,
      "dã": 1066,
      "mẽ": 1067,
      "triển": 1068,
      "triệu": 1069,
      "tấn": 1070,
      "phổ": 1071,
      "sa": 1072,
      "sơn": 1073,
      "xu": 1074,
      "Lần": 1075,
      "gói": 1076,
      "rừng": 1077,
      "tầm": 1078,
      "nổ": 1079,
      "soát": 1080,
      "mùi": 1081,
      "nhắc": 1082,
      "sơ": 1083,
      "túc": 1084,
      "đảo": 1085,
      "đài": 1086,
      "khuôn": 1087,
      "mối": 1088,
      "nguyện": 1089,
      "nội": 1090,
      "thoải": 1091,
      "trôi": 1092,
      "vali": 1093,
      "Nha": 1094,
      "cởi": 1095,
      "hoàng": 1096,
      "mộ": 1097,
      "nghiên": 1098,
      "thải": 1099,
      "tuyên": 1100,
      "Ban": 1101,
      "chiếu": 1102,
      "khắp": 1103,
      "xóm": 1104,
      "xếp": 1105,
      "lính": 1106,
      "phân": 1107,
      "tiện": 1108,
      "vết": 1109,
      "đào": 1110,
      "Bố": 1111,
      "Tây": 1112,
      "ma": 1113,
      "000": 1114,
      "dựa": 1115,
      "khoai": 1116,
      "phán": 1117,
      "thỉnh": 1118,
      "bạc": 1119,
      "hoãn": 1120,
      "làng": 1121,
      "nỗ": 1122,
      "treo": 1123,
      "trống": 1124,
      "tốc": 1125,
      "vai": 1126,
      "khăng": 1127,
      "rộng": 1128,
      "thà": 1129,
      "gà": 1130,
      "thẻ": 1131,
      "đích": 1132,
      "béo": 1133,
      "cầm": 1134,
      "jim": 1135,
      "lễ": 1136,
      "miếng": 1137,
      "trăng": 1138,
      "Chiếc": 1139,
      "dữ": 1140,
      "vạt": 1141,
      "jane": 1142,
      "Mẹ": 1143,
      "cộng": 1144,
      "dẹp": 1145,
      "cam": 1146,
      "khởi": 1147,
      "máu": 1148,
      "quý": 1149,
      "rau": 1150,
      "cốc": 1151,
      "hỏa": 1152,
      "nhặt": 1153,
      "rẻ": 1154,
      "tổng": 1155,
      "york": 1156,
      "hồi": 1157,
      "kích": 1158,
      "kẹt": 1159,
      "lệnh": 1160,
      "nam": 1161,
      "xứng": 1162,
      "bẩn": 1163,
      "chì": 1164,
      "da": 1165,
      "mô": 1166,
      "Úc": 1167,
      "Canada": 1168,
      "bò": 1169,
      "chuông": 1170,
      "gỗ": 1171,
      "kem": 1172,
      "ngàn": 1173,
      "nhấn": 1174,
      "nông": 1175,
      "đua": 1176,
      "đĩa": 1177,
      "Luân": 1178,
      "giây": 1179,
      "hỗ": 1180,
      "new": 1181,
      "nút": 1182,
      "tồn": 1183,
      "vang": 1184,
      "đuổi": 1185,
      "lát": 1186,
      "ngoan": 1187,
      "rảnh": 1188,
      "thảm": 1189,
      "tàng": 1190,
      "Đôn": 1191,
      "mù": 1192,
      "sẻ": 1193,
      "thợ": 1194,
      "cụ": 1195,
      "nụ": 1196,
      "phạt": 1197,
      "bưu": 1198,
      "hậu": 1199,
      "ẩn": 1200,
      "ngại": 1201,
      "nền": 1202,
      "thua": 1203,
      "vợt": 1204,
      "huống": 1205,
      "khôn": 1206,
      "tokyo": 1207,
      "-": 1208,
      "cỏ": 1209,
      "hấp": 1210,
      "kyoto": 1211,
      "lẫn": 1212,
      "mẫu": 1213,
      "đập": 1214,
      "đồn": 1215,
      "John": 1216,
      "cắn": 1217,
      "dầu": 1218,
      "hứng": 1219,
      "phó": 1220,
      "Vì": 1221,
      "diện": 1222,
      "giãn": 1223,
      "lành": 1224,
      "thả": 1225,
      "trực": 1226,
      "Hai": 1227,
      "cứng": 1228,
      "lưu": 1229,
      "thiếp": 1230,
      "tạm": 1231,
      "kim": 1232,
      "ngọt": 1233,
      "thổi": 1234,
      "tấm": 1235,
      "vay": 1236,
      "bê": 1237,
      "dặm": 1238,
      "ghen": 1239,
      "thuế": 1240,
      "Âu": 1241,
      "cắm": 1242,
      "gõ": 1243,
      "hạt": 1244,
      "len": 1245,
      "nguồn": 1246,
      "vận": 1247,
      "Cha": 1248,
      "Giáng": 1249,
      "dày": 1250,
      "dị": 1251,
      "khẩn": 1252,
      "phóng": 1253,
      "tô": 1254,
      "vua": 1255,
      "ướt": 1256,
      "bờ": 1257,
      "radio": 1258,
      "sót": 1259,
      "tả": 1260,
      "tịch": 1261,
      "ống": 1262,
      "thưởng": 1263,
      "mạng": 1264,
      "mỉm": 1265,
      "phi": 1266,
      "tá": 1267,
      "tín": 1268,
      "ác": 1269,
      "ôm": 1270,
      "cản": 1271,
      "hưu": 1272,
      "lối": 1273,
      "siêu": 1274,
      "sốt": 1275,
      "tị": 1276,
      "Trong": 1277,
      "chặn": 1278,
      "hồng": 1279,
      "mát": 1280,
      "reo": 1281,
      "trồng": 1282,
      "xuân": 1283,
      "dọa": 1284,
      "giặt": 1285,
      "kém": 1286,
      "mê": 1287,
      "ngưỡng": 1288,
      "nắng": 1289,
      "thẩm": 1290,
      "đồi": 1291,
      "Câu": 1292,
      "bob": 1293,
      "gồm": 1294,
      "Chính": 1295,
      "Sẽ": 1296,
      "hạ": 1297,
      "khuya": 1298,
      "khám": 1299,
      "muối": 1300,
      "trì": 1301,
      "Ý": 1302,
      "ủng": 1303,
      "cổng": 1304,
      "trao": 1305,
      "đoàn": 1306,
      "đốt": 1307,
      "chuột": 1308,
      "cất": 1309,
      "mũi": 1310,
      "sandwich": 1311,
      "đỉnh": 1312,
      "5": 1313,
      "bội": 1314,
      "luyện": 1315,
      "môi": 1316,
      "nhắm": 1317,
      "tốn": 1318,
      "đe": 1319,
      "bảng": 1320,
      "niên": 1321,
      "cướp": 1322,
      "hoang": 1323,
      "hòn": 1324,
      "Máy": 1325,
      "Vợ": 1326,
      "bồn": 1327,
      "góc": 1328,
      "nhu": 1329,
      "súp": 1330,
      "thói": 1331,
      "xã": 1332,
      "00": 1333,
      "bọn": 1334,
      "gốc": 1335,
      "hầm": 1336,
      "khô": 1337,
      "kiệt": 1338,
      "kịch": 1339,
      "lăm": 1340,
      "lục": 1341,
      "mạo": 1342,
      "ngành": 1343,
      "tỷ": 1344,
      "đâm": 1345,
      "Ngôi": 1346,
      "cú": 1347,
      "căng": 1348,
      "nâu": 1349,
      "lãnh": 1350,
      "mò": 1351,
      "săn": 1352,
      "tem": 1353,
      "gãy": 1354,
      "mảnh": 1355,
      "rác": 1356,
      "điệu": 1357,
      "3": 1358,
      "Bác": 1359,
      "mike": 1360,
      "râu": 1361,
      "đăng": 1362,
      "Ngay": 1363,
      "cậy": 1364,
      "khán": 1365,
      "thập": 1366,
      "trạm": 1367,
      "tuân": 1368,
      "đuối": 1369,
      "Nhà": 1370,
      "chứa": 1371,
      "giảng": 1372,
      "gợi": 1373,
      "khát": 1374,
      "linh": 1375,
      "sắt": 1376,
      "thiệt": 1377,
      "tò": 1378,
      "web": 1379,
      "đa": 1380,
      "đính": 1381,
      "dọc": 1382,
      "jackson": 1383,
      "rào": 1384,
      "sốc": 1385,
      "Đứa": 1386,
      "Tổng": 1387,
      "bụi": 1388,
      "jack": 1389,
      "kêu": 1390,
      "lười": 1391,
      "mây": 1392,
      "nha": 1393,
      "rẽ": 1394,
      "sô": 1395,
      "tan": 1396,
      "thủy": 1397,
      "tỏ": 1398,
      "20": 1399,
      "Cái": 1400,
      "bạo": 1401,
      "hiệp": 1402,
      "nhiễm": 1403,
      "bơ": 1404,
      "dì": 1405,
      "osaka": 1406,
      "bar": 1407,
      "bát": 1408,
      "phấn": 1409,
      "pin": 1410,
      "truyện": 1411,
      "trần": 1412,
      "vã": 1413,
      "vùng": 1414,
      "điền": 1415,
      "1": 1416,
      "6": 1417,
      "hoảng": 1418,
      "khói": 1419,
      "phức": 1420,
      "đáp": 1421,
      "chiếm": 1422,
      "cúi": 1423,
      "góp": 1424,
      "hùng": 1425,
      "kiểu": 1426,
      "kệ": 1427,
      "mt": 1428,
      "màn": 1429,
      "trừng": 1430,
      "ung": 1431,
      "đớn": 1432,
      "hôi": 1433,
      "kẹo": 1434,
      "mọc": 1435,
      "pha": 1436,
      "pizza": 1437,
      "thăng": 1438,
      "trùng": 1439,
      "xăng": 1440,
      "100": 1441,
      "họa": 1442,
      "kate": 1443,
      "lò": 1444,
      "thái": 1445,
      "tàn": 1446,
      "búp": 1447,
      "cấm": 1448,
      "gối": 1449,
      "khuyến": 1450,
      "lầu": 1451,
      "rỗng": 1452,
      "biếng": 1453,
      "niệm": 1454,
      "vâng": 1455,
      "vĩ": 1456,
      "Ấn": 1457,
      "Chỉ": 1458,
      "Kỳ": 1459,
      "chỉnh": 1460,
      "golf": 1461,
      "khứ": 1462,
      "rắn": 1463,
      "ào": 1464,
      "Tên": 1465,
      "chua": 1466,
      "hận": 1467,
      "phiên": 1468,
      "quảng": 1469,
      "thước": 1470,
      "Độ": 1471,
      "đếm": 1472,
      "7": 1473,
      "chúa": 1474,
      "gật": 1475,
      "khai": 1476,
      "lão": 1477,
      "lộ": 1478,
      "lội": 1479,
      "mắng": 1480,
      "nhát": 1481,
      "nộp": 1482,
      "dũng": 1483,
      "lau": 1484,
      "lộn": 1485,
      "mồ": 1486,
      "ngược": 1487,
      "phẫu": 1488,
      "rồ": 1489,
      "thiệp": 1490,
      "thắt": 1491,
      "trích": 1492,
      "tươi": 1493,
      "ổ": 1494,
      "Hoa": 1495,
      "chìm": 1496,
      "cạo": 1497,
      "dần": 1498,
      "gián": 1499,
      "hư": 1500,
      "nối": 1501,
      "tony": 1502,
      "vở": 1503,
      "xé": 1504,
      "đấy": 1505,
      "Theo": 1506,
      "bày": 1507,
      "dung": 1508,
      "dương": 1509,
      "hước": 1510,
      "lao": 1511,
      "rót": 1512,
      "song": 1513,
      "sóng": 1514,
      "tròn": 1515,
      "ủy": 1516,
      "Tàu": 1517,
      "Xin": 1518,
      "bó": 1519,
      "gọn": 1520,
      "rủi": 1521,
      "sương": 1522,
      "tán": 1523,
      "đòi": 1524,
      "đạn": 1525,
      "găng": 1526,
      "lượt": 1527,
      "lỏng": 1528,
      "ngột": 1529,
      "thí": 1530,
      "truy": 1531,
      "đàm": 1532,
      "gương": 1533,
      "khiếu": 1534,
      "ngào": 1535,
      "nâng": 1536,
      "quê": 1537,
      "sợi": 1538,
      "thằng": 1539,
      "voi": 1540,
      "đoạn": 1541,
      "8": 1542,
      "bắc": 1543,
      "cưỡng": 1544,
      "email": 1545,
      "fuji": 1546,
      "loạn": 1547,
      "ro": 1548,
      "sứ": 1549,
      "văng": 1550,
      "vỗ": 1551,
      "Gần": 1552,
      "Nghe": 1553,
      "bù": 1554,
      "lưỡi": 1555,
      "lặp": 1556,
      "nhàm": 1557,
      "nản": 1558,
      "thắn": 1559,
      "chở": 1560,
      "giám": 1561,
      "hương": 1562,
      "kiêng": 1563,
      "lan": 1564,
      "lặn": 1565,
      "nhạt": 1566,
      "Đừng": 1567,
      "Nga": 1568,
      "bì": 1569,
      "cận": 1570,
      "london": 1571,
      "loài": 1572,
      "rổ": 1573,
      "tháo": 1574,
      "thề": 1575,
      "tùy": 1576,
      "ám": 1577,
      "đạc": 1578,
      "đỗ": 1579,
      "đức": 1580,
      "%": 1581,
      "Phi": 1582,
      "gấu": 1583,
      "khổ": 1584,
      "lĩnh": 1585,
      "mét": 1586,
      "sét": 1587,
      "đo": 1588,
      "đống": 1589,
      "bạn": 1590,
      "biên": 1591,
      "chăn": 1592,
      "kín": 1593,
      "ngửi": 1594,
      "phận": 1595,
      "quyển": 1596,
      "quầy": 1597,
      "sánh": 1598,
      "xách": 1599,
      "bom": 1600,
      "buông": 1601,
      "bốc": 1602,
      "hoại": 1603,
      "mại": 1604,
      "sôi": 1605,
      "tộc": 1606,
      "Rõ": 1607,
      "giai": 1608,
      "gắn": 1609,
      "nancy": 1610,
      "ngầm": 1611,
      "rỉ": 1612,
      "smith": 1613,
      "tảng": 1614,
      "xương": 1615,
      "Cảm": 1616,
      "bang": 1617,
      "bùng": 1618,
      "chẳng": 1619,
      "giơ": 1620,
      "lang": 1621,
      "mạch": 1622,
      "nghề": 1623,
      "ngô": 1624,
      "sofa": 1625,
      "sủa": 1626,
      "thám": 1627,
      "đắp": 1628,
      "đẻ": 1629,
      "Cuối": 1630,
      "Hy": 1631,
      "Tất": 1632,
      "bổ": 1633,
      "chiên": 1634,
      "co": 1635,
      "cưỡi": 1636,
      "cược": 1637,
      "george": 1638,
      "hawaii": 1639,
      "hỗn": 1640,
      "lông": 1641,
      "lận": 1642,
      "lốp": 1643,
      "nến": 1644,
      "ong": 1645,
      "phô": 1646,
      "sưởi": 1647,
      "trèo": 1648,
      "video": 1649,
      "vứt": 1650,
      "Đã": 1651,
      "đáo": 1652,
      "chừng": 1653,
      "hải": 1654,
      "khảo": 1655,
      "mềm": 1656,
      "nghiện": 1657,
      "ngẩn": 1658,
      "ngớ": 1659,
      "tang": 1660,
      "thạo": 1661,
      "tiễn": 1662,
      "tràn": 1663,
      "địch": 1664,
      "đốc": 1665,
      "Lúc": 1666,
      "New": 1667,
      "bỏng": 1668,
      "háo": 1669,
      "hức": 1670,
      "khen": 1671,
      "trầm": 1672,
      "trụ": 1673,
      "tung": 1674,
      "xế": 1675,
      "ủi": 1676,
      "cám": 1677,
      "cương": 1678,
      "dạng": 1679,
      "hokkaido": 1680,
      "lincoln": 1681,
      "liệt": 1682,
      "ngập": 1683,
      "nở": 1684,
      "tráng": 1685,
      "ẩm": 1686,
      "50": 1687,
      "Dường": 1688,
      "Tiếng": 1689,
      "chicago": 1690,
      "chẽ": 1691,
      "lật": 1692,
      "thánh": 1693,
      "tật": 1694,
      "ép": 1695,
      "đấm": 1696,
      "ấu": 1697,
      "Thái": 1698,
      "bách": 1699,
      "mực": 1700,
      "nhõm": 1701,
      "nô": 1702,
      "tuyển": 1703,
      "4": 1704,
      "Cuộc": 1705,
      "Lạp": 1706,
      "ao": 1707,
      "chôn": 1708,
      "cơm": 1709,
      "dụ": 1710,
      "hiến": 1711,
      "ho": 1712,
      "jean": 1713,
      "móc": 1714,
      "nhé": 1715,
      "rạp": 1716,
      "thỏ": 1717,
      "vẫy": 1718,
      "vặt": 1719,
      "đố": 1720,
      "500": 1721,
      "cừu": 1722,
      "lạm": 1723,
      "ngợi": 1724,
      "ok": 1725,
      "sảnh": 1726,
      "tái": 1727,
      "viễn": 1728,
      "vải": 1729,
      "Ăn": 1730,
      "Cuốn": 1731,
      "Cảnh": 1732,
      "Hôm": 1733,
      "Mọi": 1734,
      "Thụy": 1735,
      "alice": 1736,
      "chén": 1737,
      "cuồng": 1738,
      "côn": 1739,
      "dưỡng": 1740,
      "dập": 1741,
      "gàng": 1742,
      "huy": 1743,
      "hồn": 1744,
      "in": 1745,
      "khoảnh": 1746,
      "liếc": 1747,
      "mạn": 1748,
      "ngang": 1749,
      "nhường": 1750,
      "rũ": 1751,
      "sưu": 1752,
      "thách": 1753,
      "túy": 1754,
      "xâm": 1755,
      "Đại": 1756,
      "9": 1757,
      "Bao": 1758,
      "bi": 1759,
      "binh": 1760,
      "bột": 1761,
      "chép": 1762,
      "dội": 1763,
      "hâm": 1764,
      "mệnh": 1765,
      "nhổ": 1766,
      "não": 1767,
      "run": 1768,
      "rung": 1769,
      "sáo": 1770,
      "trói": 1771,
      "violin": 1772,
      "xô": 1773,
      "đền": 1774,
      "cháu": 1775,
      "chải": 1776,
      "cóc": 1777,
      "dại": 1778,
      "hẹp": 1779,
      "khiển": 1780,
      "lăn": 1781,
      "lợn": 1782,
      "mày": 1783,
      "ngây": 1784,
      "nhạy": 1785,
      "phỏng": 1786,
      "râm": 1787,
      "séc": 1788,
      "sụp": 1789,
      "thầm": 1790,
      "thụ": 1791,
      "xà": 1792,
      "Nam": 1793,
      "biện": 1794,
      "bực": 1795,
      "cookie": 1796,
      "gầy": 1797,
      "gậy": 1798,
      "hiển": 1799,
      "kho": 1800,
      "khúc": 1801,
      "khối": 1802,
      "lúa": 1803,
      "mớ": 1804,
      "phú": 1805,
      "salad": 1806,
      "suất": 1807,
      "vỏ": 1808,
      "đuôi": 1809,
      "độn": 1810,
      "Cho": 1811,
      "Chồng": 1812,
      "chật": 1813,
      "chọc": 1814,
      "cạn": 1815,
      "dâu": 1816,
      "dỗ": 1817,
      "gỡ": 1818,
      "lều": 1819,
      "mi": 1820,
      "mỹ": 1821,
      "nát": 1822,
      "nại": 1823,
      "suýt": 1824,
      "xưa": 1825,
      "điệp": 1826,
      "đắn": 1827,
      "Bà": 1828,
      "Bất": 1829,
      "Mỗi": 1830,
      "Nước": 1831,
      "chủng": 1832,
      "cưng": 1833,
      "dán": 1834,
      "dính": 1835,
      "dịp": 1836,
      "giật": 1837,
      "gạo": 1838,
      "huấn": 1839,
      "khấu": 1840,
      "nhịn": 1841,
      "quét": 1842,
      "trộn": 1843,
      "tố": 1844,
      "xóa": 1845,
      "ân": 1846,
      "11": 1847,
      "Cả": 1848,
      "Mất": 1849,
      "album": 1850,
      "bẫy": 1851,
      "cay": 1852,
      "cát": 1853,
      "dịu": 1854,
      "giỏ": 1855,
      "gác": 1856,
      "gôn": 1857,
      "hèn": 1858,
      "lắc": 1859,
      "móng": 1860,
      "nghiền": 1861,
      "nôn": 1862,
      "quái": 1863,
      "tưới": 1864,
      "xoay": 1865,
      "Đối": 1866,
      "Đột": 1867,
      "đảng": 1868,
      "$": 1869,
      "'": 1870,
      "bể": 1871,
      "cỡ": 1872,
      "họng": 1873,
      "kèm": 1874,
      "lam": 1875,
      "lũ": 1876,
      "lụt": 1877,
      "miền": 1878,
      "má": 1879,
      "nhuận": 1880,
      "nháy": 1881,
      "nhạo": 1882,
      "nhợt": 1883,
      "quyến": 1884,
      "rèm": 1885,
      "thùng": 1886,
      "tướng": 1887,
      "tỏa": 1888,
      "ván": 1889,
      "Ở": 1890,
      "Bắc": 1891,
      "Giá": 1892,
      "Nói": 1893,
      "bào": 1894,
      "chuyền": 1895,
      "chuỗi": 1896,
      "hang": 1897,
      "hít": 1898,
      "kháng": 1899,
      "khỉ": 1900,
      "km": 1901,
      "lùi": 1902,
      "mẻ": 1903,
      "mỏng": 1904,
      "ranh": 1905,
      "ruồi": 1906,
      "thiểu": 1907,
      "tiệm": 1908,
      "bồ": 1909,
      "giọt": 1910,
      "jones": 1911,
      "mã": 1912,
      "ngũ": 1913,
      "thắp": 1914,
      "trúng": 1915,
      "tuyến": 1916,
      "tạnh": 1917,
      "tống": 1918,
      "vặn": 1919,
      "Á": 1920,
      "Đi": 1921,
      ",\"": 1922,
      "300": 1923,
      "Châu": 1924,
      "York": 1925,
      "ann": 1926,
      "bồi": 1927,
      "game": 1928,
      "giáng": 1929,
      "gạt": 1930,
      "kobe": 1931,
      "nhai": 1932,
      "nhét": 1933,
      "nhấp": 1934,
      "pháo": 1935,
      "sếp": 1936,
      "tháp": 1937,
      "vòi": 1938,
      "xì": 1939,
      "Lan": 1940,
      "Mãi": 1941,
      "Nhiều": 1942,
      "bấm": 1943,
      "chay": 1944,
      "chấm": 1945,
      "dáng": 1946,
      "inch": 1947,
      "khoe": 1948,
      "nghịch": 1949,
      "ngắt": 1950,
      "nhục": 1951,
      "san": 1952,
      "trúc": 1953,
      "tết": 1954,
      "vững": 1955,
      "đáy": 1956,
      "Jane": 1957,
      "Mặc": 1958,
      "bít": 1959,
      "bề": 1960,
      "chuồng": 1961,
      "dưa": 1962,
      "giam": 1963,
      "hời": 1964,
      "jazz": 1965,
      "khiêm": 1966,
      "khiêu": 1967,
      "khổng": 1968,
      "kê": 1969,
      "làn": 1970,
      "lãm": 1971,
      "lưỡng": 1972,
      "lồ": 1973,
      "mạc": 1974,
      "mập": 1975,
      "mờ": 1976,
      "ngần": 1977,
      "nắp": 1978,
      "nứt": 1979,
      "s": 1980,
      "thôn": 1981,
      "thượng": 1982,
      "tuy": 1983,
      "tân": 1984,
      "vân": 1985,
      "vần": 1986,
      "vắt": 1987,
      "điếu": 1988,
      "đắng": 1989,
      "ưu": 1990,
      "Thôi": 1991,
      "Thỉnh": 1992,
      "Xe": 1993,
      "báu": 1994,
      "bến": 1995,
      "cd": 1996,
      "chu": 1997,
      "chuối": 1998,
      "chợ": 1999,
      "còi": 2000,
      "khoán": 2001,
      "kèn": 2002,
      "lược": 2003,
      "meg": 2004,
      "mép": 2005,
      "nao": 2006,
      "nho": 2007,
      "nhút": 2008,
      "nếm": 2009,
      "rán": 2010,
      "rưỡi": 2011,
      "rốt": 2012,
      "trú": 2013,
      "vinh": 2014,
      "washington": 2015,
      "Điện": 2016,
      "điếc": 2017,
      "12": 2018,
      "200": 2019,
      "bã": 2020,
      "bướm": 2021,
      "choáng": 2022,
      "chèo": 2023,
      "chước": 2024,
      "diễu": 2025,
      "dr": 2026,
      "hệt": 2027,
      "khuỷu": 2028,
      "lờ": 2029,
      "mayuko": 2030,
      "nhốt": 2031,
      "nhựa": 2032,
      "nề": 2033,
      "phanh": 2034,
      "phổi": 2035,
      "quỹ": 2036,
      "than": 2037,
      "thối": 2038,
      "tour": 2039,
      "túng": 2040,
      "u": 2041,
      "xám": 2042,
      "xăm": 2043,
      "Em": 2044,
      "Hiện": 2045,
      "Là": 2046,
      "Mexico": 2047,
      "Trông": 2048,
      "brazil": 2049,
      "bùn": 2050,
      "cai": 2051,
      "cài": 2052,
      "duyệt": 2053,
      "dạ": 2054,
      "gạch": 2055,
      "hiên": 2056,
      "huýt": 2057,
      "hẳn": 2058,
      "kiềm": 2059,
      "laurie": 2060,
      "lướt": 2061,
      "lấp": 2062,
      "ngực": 2063,
      "nhuộm": 2064,
      "nhện": 2065,
      "nén": 2066,
      "nồi": 2067,
      "quang": 2068,
      "rome": 2069,
      "rò": 2070,
      "su": 2071,
      "susan": 2072,
      "sushi": 2073,
      "tùng": 2074,
      "vuông": 2075,
      "yumi": 2076,
      "đúc": 2077,
      "ảo": 2078,
      "ức": 2079,
      "choàng": 2080,
      "chặng": 2081,
      "cúm": 2082,
      "dư": 2083,
      "giếng": 2084,
      "gầm": 2085,
      "hoài": 2086,
      "khung": 2087,
      "kìm": 2088,
      "lê": 2089,
      "mỏ": 2090,
      "mốt": 2091,
      "mộng": 2092,
      "nghìn": 2093,
      "ngất": 2094,
      "ngọc": 2095,
      "nhãn": 2096,
      "nuốt": 2097,
      "phẳng": 2098,
      "vong": 2099,
      "xí": 2100,
      "Đánh": 2101,
      "đan": 2102,
      "15": 2103,
      "Ngày": 2104,
      "Vấn": 2105,
      "bám": 2106,
      "bầm": 2107,
      "bắp": 2108,
      "chấn": 2109,
      "khinh": 2110,
      "liều": 2111,
      "nagoya": 2112,
      "ngấy": 2113,
      "ngụm": 2114,
      "nồng": 2115,
      "phộng": 2116,
      "phớt": 2117,
      "sầm": 2118,
      "thèm": 2119,
      "thỉu": 2120,
      "tẩy": 2121,
      "vây": 2122,
      "vĩnh": 2123,
      "đun": 2124,
      "Betty": 2125,
      "Bữa": 2126,
      "Hàn": 2127,
      "Nhân": 2128,
      "dám": 2129,
      "gội": 2130,
      "kênh": 2131,
      "loạt": 2132,
      "lucy": 2133,
      "lô": 2134,
      "mến": 2135,
      "nhàng": 2136,
      "nảy": 2137,
      "paul": 2138,
      "quyên": 2139,
      "rỗi": 2140,
      "sung": 2141,
      "thuần": 2142,
      "thơm": 2143,
      "trán": 2144,
      "trưng": 2145,
      "40": 2146,
      "Ba": 2147,
      "Kinh": 2148,
      "Năm": 2149,
      "Trò": 2150,
      "Trước": 2151,
      "búa": 2152,
      "bịt": 2153,
      "bừa": 2154,
      "chanh": 2155,
      "chồn": 2156,
      "cáu": 2157,
      "cúp": 2158,
      "cảng": 2159,
      "cống": 2160,
      "cớ": 2161,
      "dứt": 2162,
      "huyết": 2163,
      "hề": 2164,
      "luộc": 2165,
      "lén": 2166,
      "mexico": 2167,
      "mải": 2168,
      "quỳ": 2169,
      "ruột": 2170,
      "rèn": 2171,
      "siêng": 2172,
      "triết": 2173,
      "trật": 2174,
      "tím": 2175,
      "tởm": 2176,
      "ôn": 2177,
      "đam": 2178,
      "đinh": 2179,
      "25": 2180,
      "Bình": 2181,
      "Chào": 2182,
      "Cánh": 2183,
      "Sĩ": 2184,
      "bong": 2185,
      "bế": 2186,
      "hiếu": 2187,
      "khoang": 2188,
      "khỏa": 2189,
      "khớp": 2190,
      "lui": 2191,
      "lúng": 2192,
      "lắp": 2193,
      "lẻo": 2194,
      "màng": 2195,
      "nara": 2196,
      "nghiệt": 2197,
      "nhịp": 2198,
      "nọ": 2199,
      "rên": 2200,
      "rực": 2201,
      "suối": 2202,
      "súc": 2203,
      "thiêu": 2204,
      "thưa": 2205,
      "tiềm": 2206,
      "trá": 2207,
      "váng": 2208,
      "whisky": 2209,
      "xá": 2210,
      "xả": 2211,
      "đẳng": 2212,
      "ơi": 2213,
      "24": 2214,
      "Brazil": 2215,
      "Cách": 2216,
      "Dương": 2217,
      "Latin": 2218,
      "TV": 2219,
      "bìa": 2220,
      "bướng": 2221,
      "bậc": 2222,
      "bỉnh": 2223,
      "c": 2224,
      "cường": 2225,
      "diệt": 2226,
      "dắt": 2227,
      "dột": 2228,
      "fan": 2229,
      "gọt": 2230,
      "gục": 2231,
      "hả": 2232,
      "internet": 2233,
      "khao": 2234,
      "khuấy": 2235,
      "linda": 2236,
      "muỗi": 2237,
      "múa": 2238,
      "ngáy": 2239,
      "ngợm": 2240,
      "nhấc": 2241,
      "ri": 2242,
      "rock": 2243,
      "rậm": 2244,
      "se": 2245,
      "sạc": 2246,
      "thịnh": 2247,
      "tước": 2248,
      "va": 2249,
      "vít": 2250,
      "vấp": 2251,
      "vốn": 2252,
      "xổ": 2253,
      "Điển": 2254,
      "đương": 2255,
      "!\"": 2256,
      "18": 2257,
      "Bức": 2258,
      "Cập": 2259,
      "Mục": 2260,
      "Rốt": 2261,
      "angeles": 2262,
      "buôn": 2263,
      "bóp": 2264,
      "california": 2265,
      "cột": 2266,
      "dơi": 2267,
      "giục": 2268,
      "hạng": 2269,
      "id": 2270,
      "ipad": 2271,
      "khoanh": 2272,
      "khẳng": 2273,
      "khẽ": 2274,
      "kiêu": 2275,
      "los": 2276,
      "lùng": 2277,
      "mòn": 2278,
      "nghiêng": 2279,
      "nhượng": 2280,
      "nét": 2281,
      "rãi": 2282,
      "rỡ": 2283,
      "tanaka": 2284,
      "thai": 2285,
      "thoáng": 2286,
      "thò": 2287,
      "trơn": 2288,
      "tê": 2289,
      "tụ": 2290,
      "visa": 2291,
      "đũa": 2292,
      "Dù": 2293,
      "Judy": 2294,
      "Ngoài": 2295,
      "Phòng": 2296,
      "Thành": 2297,
      "aspirin": 2298,
      "cuộn": 2299,
      "côi": 2300,
      "eo": 2301,
      "esperanto": 2302,
      "francisco": 2303,
      "fred": 2304,
      "giẫm": 2305,
      "hamburger": 2306,
      "heo": 2307,
      "hoạn": 2308,
      "hung": 2309,
      "hàm": 2310,
      "hái": 2311,
      "jiro": 2312,
      "keo": 2313,
      "kỉnh": 2314,
      "lẻn": 2315,
      "lồng": 2316,
      "maria": 2317,
      "mánh": 2318,
      "mỉa": 2319,
      "ngạo": 2320,
      "nhăn": 2321,
      "nạ": 2322,
      "oh": 2323,
      "oxy": 2324,
      "peter": 2325,
      "phông": 2326,
      "phối": 2327,
      "quặc": 2328,
      "robert": 2329,
      "ráp": 2330,
      "thoái": 2331,
      "trào": 2332,
      "trêu": 2333,
      "vỉa": 2334,
      "ếch": 2335,
      "ớt": 2336,
      "13": 2337,
      "Bạn": 2338,
      "Công": 2339,
      "Trên": 2340,
      "Vâng": 2341,
      "bịch": 2342,
      "chéo": 2343,
      "chục": 2344,
      "cong": 2345,
      "gãi": 2346,
      "hà": 2347,
      "hói": 2348,
      "khan": 2349,
      "khuất": 2350,
      "lố": 2351,
      "manh": 2352,
      "mộc": 2353,
      "ngừa": 2354,
      "nhộn": 2355,
      "no": 2356,
      "nộ": 2357,
      "phiêu": 2358,
      "phun": 2359,
      "phím": 2360,
      "roger": 2361,
      "roosevelt": 2362,
      "rè": 2363,
      "rụt": 2364,
      "thìa": 2365,
      "thạch": 2366,
      "virus": 2367,
      "vương": 2368,
      "vọt": 2369,
      "xui": 2370,
      "xáo": 2371,
      "xích": 2372,
      "xông": 2373,
      "úc": 2374,
      "Đôi": 2375,
      "đà": 2376,
      "đậm": 2377,
      "đế": 2378,
      "đới": 2379,
      "16": 2380,
      "Chuyến": 2381,
      "Mặt": 2382,
      "Trời": 2383,
      "Zealand": 2384,
      "củ": 2385,
      "facebook": 2386,
      "feet": 2387,
      "gas": 2388,
      "ghê": 2389,
      "gũi": 2390,
      "hoan": 2391,
      "huệ": 2392,
      "hắt": 2393,
      "jefferson": 2394,
      "kg": 2395,
      "khéo": 2396,
      "khóe": 2397,
      "léo": 2398,
      "lót": 2399,
      "lường": 2400,
      "michael": 2401,
      "mài": 2402,
      "mãn": 2403,
      "narita": 2404,
      "ngẫu": 2405,
      "ngộ": 2406,
      "ngửa": 2407,
      "nhánh": 2408,
      "nín": 2409,
      "nạp": 2410,
      "phé": 2411,
      "quẩn": 2412,
      "rụi": 2413,
      "sẹo": 2414,
      "thầy": 2415,
      "trục": 2416,
      "tu": 2417,
      "vitamin": 2418,
      "vách": 2419,
      "xẻo": 2420,
      "yokoween": 2421,
      "đoan": 2422,
      "đẫm": 2423,
      "Ước": 2424,
      "ấp": 2425,
      "70": 2426,
      "Bộ": 2427,
      "Hầu": 2428,
      "Như": 2429,
      "Rất": 2430,
      "Rập": 2431,
      "Thẩm": 2432,
      "Thế": 2433,
      "Thủ": 2434,
      "Thứ": 2435,
      "Tuy": 2436,
      "Uống": 2437,
      "bina": 2438,
      "bôi": 2439,
      "bơm": 2440,
      "bẩm": 2441,
      "canada": 2442,
      "chà": 2443,
      "châm": 2444,
      "chớp": 2445,
      "cào": 2446,
      "cưa": 2447,
      "duyên": 2448,
      "dốc": 2449,
      "dở": 2450,
      "euro": 2451,
      "fax": 2452,
      "gân": 2453,
      "halloween": 2454,
      "ham": 2455,
      "hẻm": 2456,
      "joe": 2457,
      "kyushu": 2458,
      "kì": 2459,
      "kẹp": 2460,
      "lon": 2461,
      "lãi": 2462,
      "man": 2463,
      "ngắm": 2464,
      "ngứa": 2465,
      "ninh": 2466,
      "nạt": 2467,
      "nấm": 2468,
      "nới": 2469,
      "pound": 2470,
      "rẩy": 2471,
      "shot": 2472,
      "sảng": 2473,
      "thự": 2474,
      "trinh": 2475,
      "trương": 2476,
      "tát": 2477,
      "valentine": 2478,
      "vớ": 2479,
      "xiếc": 2480,
      "Để": 2481,
      "Ả": 2482,
      "ốc": 2483,
      "ủ": 2484,
      "\",": 2485,
      "CD": 2486,
      "Hàng": 2487,
      "Mùa": 2488,
      "Mắt": 2489,
      "Peter": 2490,
      "Sao": 2491,
      "brian": 2492,
      "bớt": 2493,
      "canh": 2494,
      "carol": 2495,
      "chris": 2496,
      "cò": 2497,
      "cấu": 2498,
      "cẩu": 2499,
      "cục": 2500,
      "dang": 2501,
      "dàn": 2502,
      "dê": 2503,
      "ford": 2504,
      "gắt": 2505,
      "harry": 2506,
      "hót": 2507,
      "james": 2508,
      "jimmy": 2509,
      "khía": 2510,
      "lít": 2511,
      "lũng": 2512,
      "lụa": 2513,
      "mail": 2514,
      "marathon": 2515,
      "micro": 2516,
      "muỗng": 2517,
      "mỡ": 2518,
      "nghênh": 2519,
      "nhiếp": 2520,
      "nĩa": 2521,
      "opera": 2522,
      "phào": 2523,
      "phích": 2524,
      "quận": 2525,
      "ria": 2526,
      "rụng": 2527,
      "sam": 2528,
      "sato": 2529,
      "shakespeare": 2530,
      "sói": 2531,
      "sững": 2532,
      "texas": 2533,
      "thung": 2534,
      "tri": 2535,
      "tro": 2536,
      "tròng": 2537,
      "trữ": 2538,
      "tẻ": 2539,
      "xót": 2540,
      "xộn": 2541,
      "yến": 2542,
      "út": 2543,
      "Chuyện": 2544,
      "Chàng": 2545,
      "Cá": 2546,
      "Cửa": 2547,
      "Gia": 2548,
      "Hà": 2549,
      "Hội": 2550,
      "Tòa": 2551,
      "buồm": 2552,
      "bén": 2553,
      "bạ": 2554,
      "bọ": 2555,
      "cabin": 2556,
      "cau": 2557,
      "chen": 2558,
      "chổi": 2559,
      "của": 2560,
      "cành": 2561,
      "câm": 2562,
      "cốt": 2563,
      "cồn": 2564,
      "cụt": 2565,
      "e": 2566,
      "florida": 2567,
      "gara": 2568,
      "gớm": 2569,
      "henry": 2570,
      "hit": 2571,
      "hố": 2572,
      "jessie": 2573,
      "khái": 2574,
      "két": 2575,
      "lánh": 2576,
      "lôi": 2577,
      "lượn": 2578,
      "mâu": 2579,
      "mạt": 2580,
      "ngáp": 2581,
      "náu": 2582,
      "olympic": 2583,
      "rùa": 2584,
      "son": 2585,
      "suôn": 2586,
      "sưng": 2587,
      "thuẫn": 2588,
      "toe": 2589,
      "toét": 2590,
      "tuệ": 2591,
      "viêm": 2592,
      "xay": 2593,
      "xoa": 2594,
      "xắn": 2595,
      "đắm": 2596,
      "ơ": 2597,
      "ở": 2598,
      "1960": 2599,
      "22": 2600,
      "Chúa": 2601,
      "Hải": 2602,
      "Hỏi": 2603,
      "Thượng": 2604,
      "Tóc": 2605,
      "a": 2606,
      "beng": 2607,
      "blog": 2608,
      "bổng": 2609,
      "bộn": 2610,
      "carbon": 2611,
      "chược": 2612,
      "cự": 2613,
      "diều": 2614,
      "duỗi": 2615,
      "dí": 2616,
      "dỏm": 2617,
      "fbi": 2618,
      "ghiếc": 2619,
      "gặt": 2620,
      "hanako": 2621,
      "hilton": 2622,
      "hàn": 2623,
      "hốt": 2624,
      "keiko": 2625,
      "khoan": 2626,
      "khơi": 2627,
      "khốc": 2628,
      "kìa": 2629,
      "lay": 2630,
      "logic": 2631,
      "long": 2632,
      "lơ": 2633,
      "nga": 2634,
      "nghẹt": 2635,
      "ngoạc": 2636,
      "nguyền": 2637,
      "nguệch": 2638,
      "ngùng": 2639,
      "ngặt": 2640,
      "nhược": 2641,
      "nhở": 2642,
      "niêm": 2643,
      "non": 2644,
      "nơ": 2645,
      "quãng": 2646,
      "rúc": 2647,
      "rộ": 2648,
      "rủ": 2649,
      "shinjuku": 2650,
      "sấm": 2651,
      "sờ": 2652,
      "thác": 2653,
      "thép": 2654,
      "thổ": 2655,
      "tia": 2656,
      "toa": 2657,
      "toi": 2658,
      "triều": 2659,
      "tạ": 2660,
      "uốn": 2661,
      "william": 2662,
      "wilson": 2663,
      "x": 2664,
      "xao": 2665,
      "Đông": 2666,
      "đai": 2667,
      "ầm": 2668,
      "/": 2669,
      "0": 2670,
      "150": 2671,
      "19": 2672,
      "Chân": 2673,
      "Chủ": 2674,
      "Cẩn": 2675,
      "Hồ": 2676,
      "Ken": 2677,
      "Kể": 2678,
      "Lý": 2679,
      "Mã": 2680,
      "Mười": 2681,
      "Nơi": 2682,
      "Sữa": 2683,
      "Từ": 2684,
      "Vẫn": 2685,
      "Vậy": 2686,
      "banh": 2687,
      "berlin": 2688,
      "beth": 2689,
      "bowling": 2690,
      "băm": 2691,
      "bập": 2692,
      "chảo": 2693,
      "cm": 2694,
      "cốp": 2695,
      "cựu": 2696,
      "dãy": 2697,
      "dẻ": 2698,
      "gót": 2699,
      "hi": 2700,
      "hiroshima": 2701,
      "hãng": 2702,
      "hươu": 2703,
      "hển": 2704,
      "hổn": 2705,
      "khiết": 2706,
      "khuyết": 2707,
      "lisa": 2708,
      "liền": 2709,
      "loanh": 2710,
      "một": 2711,
      "mọt": 2712,
      "ngạt": 2713,
      "nhiễu": 2714,
      "nhồi": 2715,
      "nêu": 2716,
      "nôi": 2717,
      "phác": 2718,
      "phái": 2719,
      "phước": 2720,
      "phẫn": 2721,
      "rio": 2722,
      "rât": 2723,
      "rìu": 2724,
      "rể": 2725,
      "scotland": 2726,
      "spaghetti": 2727,
      "sướng": 2728,
      "sườn": 2729,
      "ted": 2730,
      "thiền": 2731,
      "thê": 2732,
      "thể": 2733,
      "tiêm": 2734,
      "tôm": 2735,
      "tỉa": 2736,
      "van": 2737,
      "việt": 2738,
      "vươn": 2739,
      "vượng": 2740,
      "xuồng": 2741,
      "yamada": 2742,
      "yoko": 2743,
      "Áo": 2744,
      "Điểm": 2745,
      "Đồng": 2746,
      "đãi": 2747,
      "ưa": 2748,
      "60": 2749,
      ";": 2750,
      "Bánh": 2751,
      "Chris": 2752,
      "Hồi": 2753,
      "Jack": 2754,
      "Khuôn": 2755,
      "La": 2756,
      "Lời": 2757,
      "Phản": 2758,
      "Tay": 2759,
      "Trẻ": 2760,
      "Vui": 2761,
      "bóc": 2762,
      "bệ": 2763,
      "chinh": 2764,
      "chích": 2765,
      "chốt": 2766,
      "chộp": 2767,
      "cày": 2768,
      "còng": 2769,
      "cối": 2770,
      "cụm": 2771,
      "củi": 2772,
      "diêm": 2773,
      "diệu": 2774,
      "giễu": 2775,
      "helen": 2776,
      "huynh": 2777,
      "hăng": 2778,
      "hấu": 2779,
      "hụt": 2780,
      "khoái": 2781,
      "khâu": 2782,
      "khốn": 2783,
      "kén": 2784,
      "lăng": 2785,
      "lũy": 2786,
      "lưới": 2787,
      "lầy": 2788,
      "lửng": 2789,
      "monroe": 2790,
      "mưu": 2791,
      "mương": 2792,
      "mịn": 2793,
      "nai": 2794,
      "nghẹn": 2795,
      "ngước": 2796,
      "ngụ": 2797,
      "nấc": 2798,
      "oliver": 2799,
      "paulo": 2800,
      "phơi": 2801,
      "poker": 2802,
      "quát": 2803,
      "quạt": 2804,
      "ray": 2805,
      "rồng": 2806,
      "rủa": 2807,
      "sâm": 2808,
      "sỉ": 2809,
      "sủng": 2810,
      "thắc": 2811,
      "thủng": 2812,
      "thừng": 2813,
      "truồng": 2814,
      "tâng": 2815,
      "tặc": 2816,
      "tỏi": 2817,
      "vác": 2818,
      "võ": 2819,
      "vẹt": 2820,
      "xỉ": 2821,
      "xứ": 2822,
      "ây": 2823,
      "đặn": 2824,
      "đệm": 2825,
      "ồ": 2826,
      "\".": 2827,
      "14": 2828,
      "1990": 2829,
      "80": 2830,
      "Brown": 2831,
      "Chuông": 2832,
      "Cơ": 2833,
      "Do": 2834,
      "Khoảnh": 2835,
      "Liệu": 2836,
      "Mong": 2837,
      "Ngọn": 2838,
      "Nhĩ": 2839,
      "Nhưng": 2840,
      "Phải": 2841,
      "Phục": 2842,
      "Thịt": 2843,
      "Thổ": 2844,
      "Thực": 2845,
      "Trái": 2846,
      "Tình": 2847,
      "Với": 2848,
      "anne": 2849,
      "bàng": 2850,
      "bành": 2851,
      "bẹ": 2852,
      "calo": 2853,
      "cello": 2854,
      "charles": 2855,
      "chopin": 2856,
      "chĩa": 2857,
      "chầm": 2858,
      "clarinet": 2859,
      "cocktail": 2860,
      "columbus": 2861,
      "cỗ": 2862,
      "d": 2863,
      "disneyland": 2864,
      "dép": 2865,
      "dược": 2866,
      "einstein": 2867,
      "emi": 2868,
      "gai": 2869,
      "gallon": 2870,
      "gan": 2871,
      "ghép": 2872,
      "gánh": 2873,
      "góa": 2874,
      "huyện": 2875,
      "iphone": 2876,
      "jeff": 2877,
      "jesus": 2878,
      "johnson": 2879,
      "kenji": 2880,
      "khiễng": 2881,
      "khập": 2882,
      "liếm": 2883,
      "lây": 2884,
      "lõng": 2885,
      "lọ": 2886,
      "lọc": 2887,
      "mac": 2888,
      "miller": 2889,
      "miss": 2890,
      "miện": 2891,
      "mạ": 2892,
      "mẹo": 2893,
      "naoko": 2894,
      "ngâm": 2895,
      "ngầu": 2896,
      "ngẫm": 2897,
      "ngục": 2898,
      "ngụy": 2899,
      "nhàn": 2900,
      "nhàu": 2901,
      "nhòm": 2902,
      "nhói": 2903,
      "né": 2904,
      "nần": 2905,
      "okinawa": 2906,
      "pho": 2907,
      "phì": 2908,
      "picasso": 2909,
      "que": 2910,
      "rao": 2911,
      "robot": 2912,
      "ruy": 2913,
      "rập": 2914,
      "santa": 2915,
      "singapore": 2916,
      "soạn": 2917,
      "sũng": 2918,
      "sẫm": 2919,
      "sập": 2920,
      "sừng": 2921,
      "thiển": 2922,
      "thuổng": 2923,
      "thính": 2924,
      "toyota": 2925,
      "trombone": 2926,
      "trội": 2927,
      "tuxedo": 2928,
      "tuốc": 2929,
      "túp": 2930,
      "tạng": 2931,
      "tạt": 2932,
      "vodka": 2933,
      "vú": 2934,
      "xạ": 2935,
      "xửa": 2936,
      "âu": 2937,
      "điêu": 2938,
      "đãng": 2939,
      "đệ": 2940,
      "đứt": 2941,
      "%.": 2942,
      "17": 2943,
      "27": 2944,
      "35": 2945,
      "45": 2946,
      "Bệnh": 2947,
      "Bồ": 2948,
      "Chi": 2949,
      "Còn": 2950,
      "Cực": 2951,
      "Ghế": 2952,
      "Giáo": 2953,
      "Hóa": 2954,
      "Kim": 2955,
      "Nancy": 2956,
      "Nhìn": 2957,
      "Rome": 2958,
      "Sáu": 2959,
      "Sức": 2960,
      "Thống": 2961,
      "Tim": 2962,
      "Túi": 2963,
      "Viên": 2964,
      "Việt": 2965,
      "akiko": 2966,
      "b": 2967,
      "ben": 2968,
      "bẻ": 2969,
      "bọc": 2970,
      "cathy": 2971,
      "chiêm": 2972,
      "chẩn": 2973,
      "chốc": 2974,
      "cia": 2975,
      "càu": 2976,
      "cúng": 2977,
      "cằn": 2978,
      "dải": 2979,
      "dỡ": 2980,
      "ghim": 2981,
      "gi": 2982,
      "huyền": 2983,
      "hyogo": 2984,
      "héo": 2985,
      "lee": 2986,
      "lè": 2987,
      "lút": 2988,
      "lột": 2989,
      "marika": 2990,
      "mp3": 2991,
      "mr": 2992,
      "mui": 2993,
      "muôn": 2994,
      "mồi": 2995,
      "mứt": 2996,
      "ngoạn": 2997,
      "ngài": 2998,
      "ngủi": 2999,
      "nhúng": 3000,
      "nhủ": 3001,
      "nhức": 3002,
      "nixon": 3003,
      "norway": 3004,
      "nức": 3005,
      "oxford": 3006,
      "phải": 3007,
      "quàng": 3008,
      "quạ": 3009,
      "quấn": 3010,
      "quấy": 3011,
      "quỷ": 3012,
      "rôi": 3013,
      "sapporo": 3014,
      "saxophone": 3015,
      "sen": 3016,
      "sendai": 3017,
      "steve": 3018,
      "susie": 3019,
      "sáp": 3020,
      "são": 3021,
      "sấu": 3022,
      "sụt": 3023,
      "teresa": 3024,
      "thomas": 3025,
      "toạc": 3026,
      "trân": 3027,
      "trùm": 3028,
      "trọ": 3029,
      "tông": 3030,
      "ueno": 3031,
      "ufo": 3032,
      "ukulele": 3033,
      "vani": 3034,
      "vuốt": 3035,
      "vá": 3036,
      "vóc": 3037,
      "vùi": 3038,
      "vơi": 3039,
      "vả": 3040,
      "vất": 3041,
      "vịnh": 3042,
      "vồng": 3043,
      "xoáy": 3044,
      "êm": 3045,
      "Đào": 3046,
      "Được": 3047,
      "Đội": 3048,
      "đoái": 3049,
      "đè": 3050,
      "đòn": 3051,
      "đản": 3052,
      "120": 3053,
      "1939": 3054,
      "1980": 3055,
      "2003": 3056,
      "21": 3057,
      "26": 3058,
      "400": 3059,
      "Bàn": 3060,
      "Bưu": 3061,
      "Càng": 3062,
      "Căn": 3063,
      "Giữ": 3064,
      "Gọi": 3065,
      "Học": 3066,
      "Kelly": 3067,
      "Kumi": 3068,
      "Kẻ": 3069,
      "Lũ": 3070,
      "Lớp": 3071,
      "Mấy": 3072,
      "Napoleon": 3073,
      "Nhiệm": 3074,
      "Phần": 3075,
      "Quần": 3076,
      "Sally": 3077,
      "Thuyền": 3078,
      "Thẻ": 3079,
      "Vào": 3080,
      "adams": 3081,
      "banjo": 3082,
      "betty": 3083,
      "bền": 3084,
      "bọt": 3085,
      "ceo": 3086,
      "cholesterol": 3087,
      "chuộc": 3088,
      "chói": 3089,
      "chợp": 3090,
      "chợt": 3091,
      "chửi": 3092,
      "cola": 3093,
      "cúc": 3094,
      "cẩm": 3095,
      "dĩa": 3096,
      "emily": 3097,
      "flash": 3098,
      "gang": 3099,
      "ghề": 3100,
      "gram": 3101,
      "gỏng": 3102,
      "gồ": 3103,
      "hamilton": 3104,
      "hebrew": 3105,
      "hàu": 3106,
      "hách": 3107,
      "hán": 3108,
      "hô": 3109,
      "hạc": 3110,
      "i": 3111,
      "jacksons": 3112,
      "jill": 3113,
      "johnny": 3114,
      "juliet": 3115,
      "keio": 3116,
      "khay": 3117,
      "khe": 3118,
      "khoáng": 3119,
      "khuynh": 3120,
      "khôi": 3121,
      "lẻ": 3122,
      "lốc": 3123,
      "massage": 3124,
      "miệt": 3125,
      "mẩu": 3126,
      "mặn": 3127,
      "nghiến": 3128,
      "nghếch": 3129,
      "nguội": 3130,
      "ngán": 3131,
      "ngậm": 3132,
      "nhã": 3133,
      "nhằm": 3134,
      "nhột": 3135,
      "nikko": 3136,
      "nàng": 3137,
      "nỉ": 3138,
      "nốt": 3139,
      "peso": 3140,
      "phiến": 3141,
      "phật": 3142,
      "pop": 3143,
      "pudding": 3144,
      "quáng": 3145,
      "quẫn": 3146,
      "romeo": 3147,
      "rìa": 3148,
      "rơm": 3149,
      "rạng": 3150,
      "sachiko": 3151,
      "sành": 3152,
      "sấy": 3153,
      "tanh": 3154,
      "taninna": 3155,
      "tequila": 3156,
      "thich": 3157,
      "thun": 3158,
      "thâm": 3159,
      "thật": 3160,
      "thét": 3161,
      "thệ": 3162,
      "thốt": 3163,
      "trát": 3164,
      "trút": 3165,
      "tulip": 3166,
      "tóm": 3167,
      "vcr": 3168,
      "venice": 3169,
      "vienna": 3170,
      "vẹo": 3171,
      "vịt": 3172,
      "vụn": 3173,
      "vựng": 3174,
      "xôi": 3175,
      "xẻng": 3176,
      "youtube": 3177,
      "Đàn": 3178,
      "Đưa": 3179,
      "Đầu": 3180,
      "Đến": 3181,
      "Đợi": 3182,
      "đung": 3183,
      "đàng": 3184,
      "đày": 3185,
      "đùi": 3186,
      "đút": 3187,
      "được": 3188,
      "đạm": 3189,
      "1945": 3190,
      "1970": 3191,
      "2010": 3192,
      "23": 3193,
      "65": 3194,
      "800": 3195,
      "90": 3196,
      "911": 3197,
      "Beatles": 3198,
      "Beth": 3199,
      "Bên": 3200,
      "Bốn": 3201,
      "C": 3202,
      "Cám": 3203,
      "Cần": 3204,
      "Giấc": 3205,
      "Giọng": 3206,
      "Huấn": 3207,
      "Hán": 3208,
      "Internet": 3209,
      "Khói": 3210,
      "Kitô": 3211,
      "Liên": 3212,
      "Màu": 3213,
      "Ngừng": 3214,
      "Nữ": 3215,
      "Phụ": 3216,
      "Thưa": 3217,
      "Tin": 3218,
      "Tony": 3219,
      "Tối": 3220,
      "Vài": 3221,
      "Váy": 3222,
      "alexander": 3223,
      "ana": 3224,
      "argentina": 3225,
      "axit": 3226,
      "barbara": 3227,
      "bass": 3228,
      "bungee": 3229,
      "burger": 3230,
      "bỉ": 3231,
      "caesar": 3232,
      "camera": 3233,
      "cảm": 3234,
      "chui": 3235,
      "chuồn": 3236,
      "chuộng": 3237,
      "chướng": 3238,
      "chạp": 3239,
      "claus": 3240,
      "cuba": 3241,
      "cộ": 3242,
      "darwin": 3243,
      "dioxide": 3244,
      "dạn": 3245,
      "dế": 3246,
      "dứa": 3247,
      "giang": 3248,
      "gieo": 3249,
      "giông": 3250,
      "giở": 3251,
      "gán": 3252,
      "gỉ": 3253,
      "gốm": 3254,
      "hack": 3255,
      "hakone": 3256,
      "hollywood": 3257,
      "hong": 3258,
      "hoover": 3259,
      "hydro": 3260,
      "hùm": 3261,
      "hắng": 3262,
      "hổng": 3263,
      "itub": 3264,
      "jeep": 3265,
      "kabuki": 3266,
      "karate": 3267,
      "karen": 3268,
      "kennedy": 3269,
      "khuân": 3270,
      "khứu": 3271,
      "kong": 3272,
      "kếp": 3273,
      "kề": 3274,
      "laura": 3275,
      "loa": 3276,
      "luis": 3277,
      "lẩm": 3278,
      "lậu": 3279,
      "lẽo": 3280,
      "manila": 3281,
      "mario": 3282,
      "milton": 3283,
      "monica": 3284,
      "mãnh": 3285,
      "mốc": 3286,
      "neo": 3287,
      "nghẽn": 3288,
      "ngoãn": 3289,
      "ngoặt": 3290,
      "ngơ": 3291,
      "ngư": 3292,
      "ngượng": 3293,
      "ngẩng": 3294,
      "ngợp": 3295,
      "nhào": 3296,
      "nhích": 3297,
      "nhúc": 3298,
      "nhũng": 3299,
      "nhị": 3300,
      "nhọn": 3301,
      "niềng": 3302,
      "núm": 3303,
      "núng": 3304,
      "nạng": 3305,
      "nếp": 3306,
      "nớt": 3307,
      "obama": 3308,
      "oboe": 3309,
      "romania": 3310,
      "rong": 3311,
      "roy": 3312,
      "ruộng": 3313,
      "rách": 3314,
      "rám": 3315,
      "rùng": 3316,
      "sake": 3317,
      "sasayama": 3318,
      "shibuya": 3319,
      "siết": 3320,
      "sue": 3321,
      "sydney": 3322,
      "sảo": 3323,
      "sồi": 3324,
      "thau": 3325,
      "thình": 3326,
      "thấm": 3327,
      "thọ": 3328,
      "trâu": 3329,
      "táng": 3330,
      "tăm": 3331,
      "tấc": 3332,
      "tựa": 3333,
      "tựu": 3334,
      "ve": 3335,
      "viếng": 3336,
      "vo": 3337,
      "véo": 3338,
      "vạch": 3339,
      "vụng": 3340,
      "windows": 3341,
      "woozy": 3342,
      "xi": 3343,
      "xoăn": 3344,
      "xuôi": 3345,
      "xưởng": 3346,
      "Ôi": 3347,
      "át": 3348,
      "óc": 3349,
      "Đặt": 3350,
      "đên": 3351,
      "đụng": 3352,
      "ả": 3353,
      "ảm": 3354,
      "ợ": 3355,
      "123": 3356,
      "1950": 3357,
      "1972": 3358,
      "1992": 3359,
      "2008": 3360,
      "250": 3361,
      "28": 3362,
      "31": 3363,
      "33": 3364,
      "36": 3365,
      "Bia": 3366,
      "Bài": 3367,
      "Bão": 3368,
      "Cam": 3369,
      "Chúc": 3370,
      "Chẳng": 3371,
      "Chị": 3372,
      "Cây": 3373,
      "David": 3374,
      "Emily": 3375,
      "Finland": 3376,
      "Hitler": 3377,
      "Hồng": 3378,
      "Inca": 3379,
      "James": 3380,
      "Khăn": 3381,
      "Kông": 3382,
      "Mùi": 3383,
      "Mệt": 3384,
      "Nhận": 3385,
      "Này": 3386,
      "Paris": 3387,
      "Sinh": 3388,
      "Séc": 3389,
      "Số": 3390,
      "Sự": 3391,
      "Triển": 3392,
      "Trà": 3393,
      "Trận": 3394,
      "accordion": 3395,
      "alps": 3396,
      "am": 3397,
      "amazon": 3398,
      "anderson": 3399,
      "ankara": 3400,
      "ballet": 3401,
      "bassoon": 3402,
      "belgium": 3403,
      "berber": 3404,
      "bill": 3405,
      "bush": 3406,
      "bói": 3407,
      "bón": 3408,
      "bùa": 3409,
      "băn": 3410,
      "bạch": 3411,
      "bẹp": 3412,
      "bục": 3413,
      "chòm": 3414,
      "com": 3415,
      "cricket": 3416,
      "cáp": 3417,
      "cõng": 3418,
      "cọc": 3419,
      "davis": 3420,
      "de": 3421,
      "dinh": 3422,
      "douecraft": 3423,
      "duffel": 3424,
      "dâng": 3425,
      "dãi": 3426,
      "dè": 3427,
      "dò": 3428,
      "dặt": 3429,
      "dệt": 3430,
      "dời": 3431,
      "dụi": 3432,
      "dừa": 3433,
      "edo": 3434,
      "elizabeth": 3435,
      "everest": 3436,
      "franklin": 3437,
      "gay": 3438,
      "gen": 3439,
      "geneva": 3440,
      "gin": 3441,
      "giáp": 3442,
      "giòn": 3443,
      "gom": 3444,
      "gomez": 3445,
      "gừ": 3446,
      "harrison": 3447,
      "harvard": 3448,
      "hashimoto": 3449,
      "hen": 3450,
      "hiroshi": 3451,
      "huỳnh": 3452,
      "hông": 3453,
      "hĩnh": 3454,
      "hợm": 3455,
      "hợt": 3456,
      "iraq": 3457,
      "ito": 3458,
      "jenny": 3459,
      "jordan": 3460,
      "karaoke": 3461,
      "khoăn": 3462,
      "kimono": 3463,
      "liu": 3464,
      "liễu": 3465,
      "loãng": 3466,
      "lân": 3467,
      "lõi": 3468,
      "lùn": 3469,
      "lảng": 3470,
      "lảo": 3471,
      "lề": 3472,
      "lệch": 3473,
      "lứa": 3474,
      "lựu": 3475,
      "madonna": 3476,
      "madrid": 3477,
      "malaysia": 3478,
      "masaru": 3479,
      "me": 3480,
      "men": 3481,
      "meo": 3482,
      "ming": 3483,
      "moscow": 3484,
      "mozart": 3485,
      "mĩm": 3486,
      "mũm": 3487,
      "nagasaki": 3488,
      "nan": 3489,
      "nháp": 3490,
      "nhím": 3491,
      "nhô": 3492,
      "nhĩ": 3493,
      "nhấm": 3494,
      "nhằn": 3495,
      "nhẹn": 3496,
      "nick": 3497,
      "noi": 3498,
      "nuông": 3499,
      "nã": 3500,
      "năn": 3501,
      "nẻ": 3502,
      "nệm": 3503,
      "nọc": 3504,
      "nực": 3505,
      "olympics": 3506,
      "panama": 3507,
      "pedro": 3508,
      "phu": 3509,
      "pounds": 3510,
      "quyệt": 3511,
      "quất": 3512,
      "quật": 3513,
      "quỵ": 3514,
      "rap": 3515,
      "reagan": 3516,
      "roland": 3517,
      "rosa": 3518,
      "rén": 3519,
      "rít": 3520,
      "rón": 3521,
      "rễ": 3522,
      "rợ": 3523,
      "sadako": 3524,
      "sally": 3525,
      "scott": 3526,
      "soda": 3527,
      "sumo": 3528,
      "suzuki": 3529,
      "sọ": 3530,
      "sọc": 3531,
      "sỏi": 3532,
      "sởi": 3533,
      "sục": 3534,
      "tahiti": 3535,
      "takuya": 3536,
      "tam": 3537,
      "tango": 3538,
      "tatoeba": 3539,
      "taylor": 3540,
      "ten": 3541,
      "thiêng": 3542,
      "thây": 3543,
      "thạc": 3544,
      "tre": 3545,
      "tru": 3546,
      "tràng": 3547,
      "trầy": 3548,
      "trệ": 3549,
      "trọn": 3550,
      "tuông": 3551,
      "tuột": 3552,
      "tấp": 3553,
      "tụt": 3554,
      "ukraine": 3555,
      "uy": 3556,
      "việc": 3557,
      "vê": 3558,
      "wow": 3559,
      "xoắn": 3560,
      "xảo": 3561,
      "xịt": 3562,
      "xỏ": 3563,
      "yết": 3564,
      "úp": 3565,
      "Đúng": 3566,
      "đê": 3567,
      "đầm": 3568,
      "đắc": 3569,
      "đốm": 3570,
      "ư": 3571,
      "ỏi": 3572,
      "110": 3573,
      "1860": 3574,
      "1933": 3575,
      "1940": 3576,
      "1964": 3577,
      "1969": 3578,
      "1971": 3579,
      "1979": 3580,
      "1987": 3581,
      "1989": 3582,
      "1995": 3583,
      "1997": 3584,
      "1998": 3585,
      "2013": 3586,
      "29": 3587,
      "333": 3588,
      "38": 3589,
      "48": 3590,
      "Afghanistan": 3591,
      "Amy": 3592,
      "Bill": 3593,
      "Biển": 3594,
      "Bằng": 3595,
      "Cathy": 3596,
      "Chắc": 3597,
      "Croatia": 3598,
      "Cấm": 3599,
      "Cổ": 3600,
      "Của": 3601,
      "Detroit": 3602,
      "Dân": 3603,
      "Dạy": 3604,
      "Dọn": 3605,
      "Dừng": 3606,
      "George": 3607,
      "Giày": 3608,
      "Giống": 3609,
      "Hiệp": 3610,
      "Jill": 3611,
      "Joan": 3612,
      "Kansas": 3613,
      "Khu": 3614,
      "Khí": 3615,
      "Linh": 3616,
      "Loại": 3617,
      "Lính": 3618,
      "Matsuyama": 3619,
      "Na": 3620,
      "Nghĩ": 3621,
      "Ngoại": 3622,
      "Nông": 3623,
      "Oh": 3624,
      "Quả": 3625,
      "Richard": 3626,
      "Singapore": 3627,
      "Sáng": 3628,
      "Sơn": 3629,
      "The": 3630,
      "Thuốc": 3631,
      "Thông": 3632,
      "Thời": 3633,
      "Tiền": 3634,
      "Trường": 3635,
      "Trợ": 3636,
      "Tuần": 3637,
      "Tự": 3638,
      "USD": 3639,
      "Uy": 3640,
      "Viết": 3641,
      "Việc": 3642,
      "Vẻ": 3643,
      "Về": 3644,
      "Xô": 3645,
      "akira": 3646,
      "allan": 3647,
      "and": 3648,
      "andrew": 3649,
      "andy": 3650,
      "anna": 3651,
      "aoi": 3652,
      "backgammon": 3653,
      "barcelona": 3654,
      "beethoven": 3655,
      "bikini": 3656,
      "blues": 3657,
      "brandy": 3658,
      "bú": 3659,
      "băt": 3660,
      "bưởi": 3661,
      "bịp": 3662,
      "bổn": 3663,
      "carlos": 3664,
      "chỉ": 3665,
      "choạng": 3666,
      "chuck": 3667,
      "chuyện": 3668,
      "chèn": 3669,
      "chùa": 3670,
      "chả": 3671,
      "cnn": 3672,
      "cocaine": 3673,
      "cuộc": 3674,
      "cút": 3675,
      "cấy": 3676,
      "dan": 3677,
      "dazai": 3678,
      "diếp": 3679,
      "dj": 3680,
      "dạt": 3681,
      "dẫm": 3682,
      "dồn": 3683,
      "ebay": 3684,
      "eric": 3685,
      "fahrenheit": 3686,
      "ferrari": 3687,
      "g": 3688,
      "georgia": 3689,
      "giun": 3690,
      "giăm": 3691,
      "giỡn": 3692,
      "google": 3693,
      "goro": 3694,
      "graham": 3695,
      "gìn": 3696,
      "gượng": 3697,
      "hakata": 3698,
      "hamster": 3699,
      "hao": 3700,
      "hawking": 3701,
      "hudson": 3702,
      "hê": 3703,
      "hòi": 3704,
      "hưng": 3705,
      "hắn": 3706,
      "ikeda": 3707,
      "ireland": 3708,
      "javascript": 3709,
      "joseph": 3710,
      "julia": 3711,
      "julie": 3712,
      "kanda": 3713,
      "kanji": 3714,
      "kathy": 3715,
      "khiếm": 3716,
      "khuẩn": 3717,
      "khàn": 3718,
      "khử": 3719,
      "koko": 3720,
      "kép": 3721,
      "loạng": 3722,
      "lung": 3723,
      "luồng": 3724,
      "lách": 3725,
      "lẫy": 3726,
      "lằn": 3727,
      "lỏm": 3728,
      "lộng": 3729,
      "m": 3730,
      "madison": 3731,
      "marco": 3732,
      "mari": 3733,
      "marilyn": 3734,
      "mckinley": 3735,
      "miho": 3736,
      "milan": 3737,
      "miên": 3738,
      "miêu": 3739,
      "molly": 3740,
      "ms": 3741,
      "mút": 3742,
      "măng": 3743,
      "mầm": 3744,
      "mận": 3745,
      "mọng": 3746,
      "mổ": 3747,
      "mụn": 3748,
      "nagano": 3749,
      "naoki": 3750,
      "naomi": 3751,
      "newton": 3752,
      "ngai": 3753,
      "ngả": 3754,
      "ngỗng": 3755,
      "nheo": 3756,
      "nhíu": 3757,
      "nhón": 3758,
      "nhậm": 3759,
      "nhỉ": 3760,
      "nhờn": 3761,
      "nướu": 3762,
      "nấng": 3763,
      "nập": 3764,
      "nặc": 3765,
      "o": 3766,
      "ogawa": 3767,
      "p": 3768,
      "patin": 3769,
      "paula": 3770,
      "penicillin": 3771,
      "phai": 3772,
      "phao": 3773,
      "phà": 3774,
      "quăng": 3775,
      "quế": 3776,
      "r": 3777,
      "ren": 3778,
      "rhine": 3779,
      "robinson": 3780,
      "roi": 3781,
      "rình": 3782,
      "rúm": 3783,
      "rạn": 3784,
      "rải": 3785,
      "serbia": 3786,
      "shinano": 3787,
      "shinji": 3788,
      "shizuoka": 3789,
      "short": 3790,
      "skype": 3791,
      "suyễn": 3792,
      "sò": 3793,
      "sòng": 3794,
      "sùng": 3795,
      "sút": 3796,
      "taj": 3797,
      "tamori": 3798,
      "tate": 3799,
      "tempura": 3800,
      "thêu": 3801,
      "thầu": 3802,
      "thằn": 3803,
      "thẳm": 3804,
      "triệt": 3805,
      "trâm": 3806,
      "trìu": 3807,
      "trơ": 3808,
      "trỏ": 3809,
      "trụi": 3810,
      "tuổi": 3811,
      "tí": 3812,
      "tĩu": 3813,
      "tệp": 3814,
      "tọa": 3815,
      "tọc": 3816,
      "tứ": 3817,
      "vung": 3818,
      "vát": 3819,
      "vãnh": 3820,
      "vượn": 3821,
      "vạ": 3822,
      "vẹn": 3823,
      "vỉ": 3824,
      "waltz": 3825,
      "xước": 3826,
      "xược": 3827,
      "xấc": 3828,
      "yamamoto": 3829,
      "yo": 3830,
      "yếm": 3831,
      "zip": 3832,
      "ái": 3833,
      "én": 3834,
      "ăng": 3835,
      "Địa": 3836,
      "Động": 3837,
      "đúp": 3838,
      "đẩu": 3839,
      "đậy": 3840,
      "đợt": 3841,
      "ĩ": 3842,
      "ưng": 3843,
      "ập": 3844,
      "ẹp": 3845,
      "ọp": 3846,
      "ốp": 3847,
      "ớn": 3848,
      ".,": 3849,
      "...": 3850,
      ".?": 3851,
      "155": 3852,
      "160": 3853,
      "180": 3854,
      "1847": 3855,
      "1853": 3856,
      "1864": 3857,
      "1865": 3858,
      "1903": 3859,
      "1930": 3860,
      "1941": 3861,
      "1954": 3862,
      "1968": 3863,
      "1976": 3864,
      "1986": 3865,
      "2009": 3866,
      "54": 3867,
      "55": 3868,
      "600": 3869,
      "75": 3870,
      "99": 3871,
      "Actinium": 3872,
      "Atlanta": 3873,
      "Bob": 3874,
      "Báo": 3875,
      "Bơi": 3876,
      "Bắt": 3877,
      "Bởi": 3878,
      "Caesar": 3879,
      "Chiến": 3880,
      "Chú": 3881,
      "Chơi": 3882,
      "Chỗ": 3883,
      "Chữ": 3884,
      "Cookie": 3885,
      "Cầu": 3886,
      "Cố": 3887,
      "Disney": 3888,
      "Dì": 3889,
      "Dòng": 3890,
      "Dự": 3891,
      "Gì": 3892,
      "Helen": 3893,
      "Hẹn": 3894,
      "Indonesia": 3895,
      "Kato": 3896,
      "Khoai": 3897,
      "Khách": 3898,
      "Kiên": 3899,
      "Kính": 3900,
      "Luôn": 3901,
      "Massachusetts": 3902,
      "Mona": 3903,
      "Môi": 3904,
      "Natto": 3905,
      "Ngủ": 3906,
      "No": 3907,
      "Noel": 3908,
      "Nấm": 3909,
      "Quan": 3910,
      "Quyết": 3911,
      "Quân": 3912,
      "Răng": 3913,
      "Rượu": 3914,
      "Sandra": 3915,
      "Santa": 3916,
      "Selena": 3917,
      "Sắp": 3918,
      "Sở": 3919,
      "Ta": 3920,
      "Thay": 3921,
      "Thiên": 3922,
      "Thám": 3923,
      "Thị": 3924,
      "Thỏa": 3925,
      "Titanic": 3926,
      "Toàn": 3927,
      "Tracy": 3928,
      "Trang": 3929,
      "Tư": 3930,
      "Từng": 3931,
      "USB": 3932,
      "Vỏ": 3933,
      "Yên": 3934,
      "adam": 3935,
      "akita": 3936,
      "alaska": 3937,
      "albert": 3938,
      "ali": 3939,
      "alibis": 3940,
      "alister": 3941,
      "amsterdam": 3942,
      "atlantis": 3943,
      "australia": 3944,
      "bach": 3945,
      "bali": 3946,
      "barry": 3947,
      "bản": 3948,
      "bbc": 3949,
      "billy": 3950,
      "biwa": 3951,
      "biêt": 3952,
      "boa": 3953,
      "bongos": 3954,
      "boong": 3955,
      "bourbon": 3956,
      "brownies": 3957,
      "bu": 3958,
      "buchird": 3959,
      "bugi": 3960,
      "buren": 3961,
      "burr": 3962,
      "burrito": 3963,
      "buốt": 3964,
      "búng": 3965,
      "bẩy": 3966,
      "bốt": 3967,
      "bỗng": 3968,
      "calvino": 3969,
      "cambridge": 3970,
      "cassette": 3971,
      "centimet": 3972,
      "chavez": 3973,
      "chip": 3974,
      "chiêc": 3975,
      "chiết": 3976,
      "christ": 3977,
      "chài": 3978,
      "chém": 3979,
      "chùi": 3980,
      "chùm": 3981,
      "chăng": 3982,
      "chạng": 3983,
      "chấu": 3984,
      "chậu": 3985,
      "chừa": 3986,
      "chửng": 3987,
      "clinton": 3988,
      "cotton": 3989,
      "cua": 3990,
      "cán": 3991,
      "cáng": 3992,
      "cùn": 3993,
      "cũi": 3994,
      "cửa": 3995,
      "cọ": 3996,
      "cồng": 3997,
      "cửu": 3998,
      "dave": 3999,
      "david": 4000,
      "denmark": 4001,
      "derby": 4002,
      "dna": 4003,
      "dorothy": 4004,
      "dượng": 4005,
      "dấy": 4006,
      "dồi": 4007,
      "edison": 4008,
      "edward": 4009,
      "eiffel": 4010,
      "eisenhower": 4011,
      "ellie": 4012,
      "folks": 4013,
      "fukuoka": 4014,
      "gettysburg": 4015,
      "ginza": 4016,
      "giup": 4017,
      "giũ": 4018,
      "giương": 4019,
      "giẻ": 4020,
      "graffiti": 4021,
      "guinea": 4022,
      "gươm": 4023,
      "gọng": 4024,
      "haiku": 4025,
      "haiti": 4026,
      "hanshin": 4027,
      "hatchet": 4028,
      "hiền": 4029,
      "hoay": 4030,
      "hoành": 4031,
      "hybrid": 4032,
      "hân": 4033,
      "hãnh": 4034,
      "hạch": 4035,
      "hỉ": 4036,
      "hớt": 4037,
      "hủ": 4038,
      "ichiro": 4039,
      "inca": 4040,
      "iran": 4041,
      "irish": 4042,
      "italo": 4043,
      "jamaica": 4044,
      "janeiro": 4045,
      "janet": 4046,
      "joneses": 4047,
      "jr": 4048,
      "kamakura": 4049,
      "kansai": 4050,
      "karuizawa": 4051,
      "kerry": 4052,
      "kevin": 4053,
      "khong": 4054,
      "ki": 4055,
      "kimura": 4056,
      "kleenex": 4057,
      "klutz": 4058,
      "ko": 4059,
      "koizumi": 4060,
      "kumiko": 4061,
      "kuniko": 4062,
      "kyoko": 4063,
      "kềnh": 4064,
      "kỵ": 4065,
      "l": 4066,
      "lennon": 4067,
      "limo": 4068,
      "lisp": 4069,
      "loay": 4070,
      "loát": 4071,
      "lán": 4072,
      "lóe": 4073,
      "lươn": 4074,
      "lạch": 4075,
      "lặt": 4076,
      "lết": 4077,
      "lọt": 4078,
      "lỏi": 4079,
      "lở": 4080,
      "lức": 4081,
      "lữ": 4082,
      "macffy": 4083,
      "mahal": 4084,
      "mandolin": 4085,
      "marconi": 4086,
      "marcus": 4087,
      "marie": 4088,
      "mariko": 4089,
      "martha": 4090,
      "martin": 4091,
      "mass": 4092,
      "mcdonald": 4093,
      "melbourne": 4094,
      "meros": 4095,
      "mic": 4096,
      "microsoft": 4097,
      "midori": 4098,
      "miso": 4099,
      "mormon": 4100,
      "mu": 4101,
      "méo": 4102,
      "mệt": 4103,
      "mượt": 4104,
      "mảng": 4105,
      "mề": 4106,
      "mồm": 4107,
      "nghĩnh": 4108,
      "ngoáy": 4109,
      "ngoảnh": 4110,
      "nguậy": 4111,
      "ngà": 4112,
      "ngác": 4113,
      "ngông": 4114,
      "ngươi": 4115,
      "ngấn": 4116,
      "ngọ": 4117,
      "ngừ": 4118,
      "nhang": 4119,
      "nhí": 4120,
      "nhòa": 4121,
      "nhó": 4122,
      "nhóc": 4123,
      "nhảm": 4124,
      "nicholas": 4125,
      "ninja": 4126,
      "nitơ": 4127,
      "nude": 4128,
      "nòng": 4129,
      "nóc": 4130,
      "nạc": 4131,
      "ohio": 4132,
      "oi": 4133,
      "online": 4134,
      "ono": 4135,
      "osamu": 4136,
      "oscar": 4137,
      "pablo": 4138,
      "pachinko": 4139,
      "pakistan": 4140,
      "paolo": 4141,
      "patricia": 4142,
      "pepperoni": 4143,
      "perry": 4144,
      "peru": 4145,
      "petersburg": 4146,
      "phe": 4147,
      "philip": 4148,
      "phiếm": 4149,
      "phung": 4150,
      "phỉ": 4151,
      "phịch": 4152,
      "phồng": 4153,
      "phủi": 4154,
      "pint": 4155,
      "pochi": 4156,
      "protein": 4157,
      "què": 4158,
      "radar": 4159,
      "rie": 4160,
      "robin": 4161,
      "roulette": 4162,
      "russell": 4163,
      "ruồng": 4164,
      "ré": 4165,
      "rê": 4166,
      "rô": 4167,
      "rú": 4168,
      "rương": 4169,
      "rưởi": 4170,
      "rạc": 4171,
      "rầm": 4172,
      "sach": 4173,
      "sahara": 4174,
      "samurai": 4175,
      "sanda": 4176,
      "sara": 4177,
      "sarah": 4178,
      "sashimi": 4179,
      "scam": 4180,
      "scottish": 4181,
      "selena": 4182,
      "shanghai": 4183,
      "shikoku": 4184,
      "shinkansen": 4185,
      "showa": 4186,
      "siberia": 4187,
      "st": 4188,
      "stan": 4189,
      "sukiyaki": 4190,
      "switzerland": 4191,
      "sán": 4192,
      "sê": 4193,
      "sưa": 4194,
      "sự": 4195,
      "sấp": 4196,
      "sặc": 4197,
      "sếu": 4198,
      "t": 4199,
      "tab": 4200,
      "takahashi": 4201,
      "takeshi": 4202,
      "tao": 4203,
      "teen": 4204,
      "terry": 4205,
      "thoi": 4206,
      "thấu": 4207,
      "thịch": 4208,
      "tip": 4209,
      "titanic": 4210,
      "tohoku": 4211,
      "toái": 4212,
      "toát": 4213,
      "trailer": 4214,
      "trau": 4215,
      "truman": 4216,
      "trệt": 4217,
      "trừu": 4218,
      "tuba": 4219,
      "twain": 4220,
      "twitter": 4221,
      "tóe": 4222,
      "tấu": 4223,
      "tớ": 4224,
      "uỵch": 4225,
      "ven": 4226,
      "venetian": 4227,
      "vest": 4228,
      "vu": 4229,
      "vành": 4230,
      "vậy": 4231,
      "vò": 4232,
      "vòm": 4233,
      "vũng": 4234,
      "vạng": 4235,
      "vảy": 4236,
      "vắc": 4237,
      "vằn": 4238,
      "vịn": 4239,
      "wang": 4240,
      "waseda": 4241,
      "williams": 4242,
      "xua": 4243,
      "xâu": 4244,
      "xôn": 4245,
      "xẹp": 4246,
      "xỉu": 4247,
      "xổm": 4248,
      "yakitori": 4249,
      "ymca": 4250,
      "yuka": 4251,
      "yumiko": 4252,
      "yuri": 4253,
      "zombie": 4254,
      "òa": 4255,
      "ó": 4256,
      "Đám": 4257,
      "đay": 4258,
      "đoạt": 4259,
      "đẽ": 4260,
      "đốn": 4261,
      "đực": 4262,
      "Ứng": 4263,
      "!!": 4264,
      "&": 4265,
      "1000": 4266,
      "111": 4267,
      "119": 4268,
      "124": 4269,
      "1600": 4270,
      "1603": 4271,
      "1610": 4272,
      "1636": 4273,
      "1650": 4274,
      "1776": 4275,
      "1796": 4276,
      "1880": 4277,
      "1899": 4278,
      "1911": 4279,
      "1912": 4280,
      "1923": 4281,
      "1925": 4282,
      "1927": 4283,
      "1929": 4284,
      "1935": 4285,
      "1937": 4286,
      "1943": 4287,
      "1944": 4288,
      "1952": 4289,
      "1955": 4290,
      "1956": 4291,
      "1959": 4292,
      "1962": 4293,
      "1965": 4294,
      "1974": 4295,
      "1975": 4296,
      "1977": 4297,
      "1982": 4298,
      "1988": 4299,
      "1994": 4300,
      "1996": 4301,
      "1999": 4302,
      "2000": 4303,
      "2001": 4304,
      "2012": 4305,
      "308": 4306,
      "32": 4307,
      "34": 4308,
      "360": 4309,
      "37": 4310,
      "41": 4311,
      "42": 4312,
      "46": 4313,
      "58": 4314,
      "68": 4315,
      "700": 4316,
      "76": 4317,
      "81": 4318,
      "88": 4319,
      "900": 4320,
      "95": 4321,
      "97": 4322,
      "Amazon": 4323,
      "Anna": 4324,
      "Anne": 4325,
      "Ao": 4326,
      "Asem": 4327,
      "Bruce": 4328,
      "Bungari": 4329,
      "Burr": 4330,
      "Burton": 4331,
      "Bị": 4332,
      "Bọn": 4333,
      "Bỗng": 4334,
      "Calais": 4335,
      "Chung": 4336,
      "Churchill": 4337,
      "Chế": 4338,
      "Cinda": 4339,
      "Clinton": 4340,
      "Connecticut": 4341,
      "Cuba": 4342,
      "Câm": 4343,
      "Cùng": 4344,
      "Cúm": 4345,
      "Cơn": 4346,
      "Cộng": 4347,
      "Cứu": 4348,
      "Da": 4349,
      "Diêm": 4350,
      "Elvis": 4351,
      "Everest": 4352,
      "Express": 4353,
      "Gieo": 4354,
      "Giả": 4355,
      "Giờ": 4356,
      "Glenn": 4357,
      "Gặp": 4358,
      "Gửi": 4359,
      "Hamster": 4360,
      "Harmonica": 4361,
      "Hey": 4362,
      "Hillary": 4363,
      "Hoàng": 4364,
      "Hoạt": 4365,
      "Huyện": 4366,
      "Hêt": 4367,
      "Hình": 4368,
      "Hạn": 4369,
      "Hợp": 4370,
      "Jackson": 4371,
      "Jerusalem": 4372,
      "João": 4373,
      "Kate": 4374,
      "Kathy": 4375,
      "Kissinger": 4376,
      "Kiểu": 4377,
      "Kiệt": 4378,
      "Latinh": 4379,
      "Lem": 4380,
      "Luther": 4381,
      "Lắc": 4382,
      "Lắng": 4383,
      "Lễ": 4384,
      "Lọ": 4385,
      "Lối": 4386,
      "Mang": 4387,
      "Marilyn": 4388,
      "Martin": 4389,
      "May": 4390,
      "Maya": 4391,
      "Mike": 4392,
      "Muốn": 4393,
      "Mà": 4394,
      "Mày": 4395,
      "Máu": 4396,
      "Môn": 4397,
      "Mông": 4398,
      "Mĩ": 4399,
      "Mũi": 4400,
      "Mạch": 4401,
      "Mới": 4402,
      "Nghỉ": 4403,
      "Ngân": 4404,
      "Ngôn": 4405,
      "Ngư": 4406,
      "Nhiệt": 4407,
      "Nhóm": 4408,
      "Nhấp": 4409,
      "Niken": 4410,
      "Nile": 4411,
      "Nội": 4412,
      "Paul": 4413,
      "Philippines": 4414,
      "Phó": 4415,
      "Phổ": 4416,
      "Pin": 4417,
      "Polk": 4418,
      "Quá": 4419,
      "Robert": 4420,
      "Robot": 4421,
      "Rôma": 4422,
      "Spencer": 4423,
      "Syria": 4424,
      "Súng": 4425,
      "Sản": 4426,
      "Sống": 4427,
      "Takeo": 4428,
      "Thames": 4429,
      "Than": 4430,
      "Thomas": 4431,
      "Thà": 4432,
      "Thảm": 4433,
      "Thấy": 4434,
      "Tiên": 4435,
      "Tiểu": 4436,
      "Tolstoy": 4437,
      "Tomoko": 4438,
      "Towada": 4439,
      "Triều": 4440,
      "Truman": 4441,
      "Tránh": 4442,
      "Trả": 4443,
      "Trở": 4444,
      "Tìm": 4445,
      "Tạm": 4446,
      "Tấm": 4447,
      "Tập": 4448,
      "Tổ": 4449,
      "Tớ": 4450,
      "Ukraina": 4451,
      "Vương": 4452,
      "Vị": 4453,
      "Vịt": 4454,
      "Vụ": 4455,
      "X": 4456,
      "Yêu": 4457,
      "aah": 4458,
      "aaron": 4459,
      "abc": 4460,
      "abel": 4461,
      "abraham": 4462,
      "agar": 4463,
      "akagawa": 4464,
      "al": 4465,
      "alan": 4466,
      "alex": 4467,
      "alfred": 4468,
      "als": 4469,
      "amidan": 4470,
      "amp": 4471,
      "angola": 4472,
      "annie": 4473,
      "anthony": 4474,
      "anyway": 4475,
      "aomori": 4476,
      "apple": 4477,
      "armenia": 4478,
      "armstrong": 4479,
      "arthur": 4480,
      "asahi": 4481,
      "ashburton": 4482,
      "aso": 4483,
      "athens": 4484,
      "audiobook": 4485,
      "bagpipes": 4486,
      "balkan": 4487,
      "bangkok": 4488,
      "barack": 4489,
      "baritone": 4490,
      "barney": 4491,
      "bellboy": 4492,
      "benjamin": 4493,
      "bernard": 4494,
      "bin": 4495,
      "bị": 4496,
      "biếm": 4497,
      "bonaparte": 4498,
      "bosnia": 4499,
      "brown": 4500,
      "bruce": 4501,
      "bugle": 4502,
      "bum": 4503,
      "buồng": 4504,
      "bá": 4505,
      "bênh": 4506,
      "bạt": 4507,
      "bấy": 4508,
      "bầy": 4509,
      "bịa": 4510,
      "bừng": 4511,
      "cameron": 4512,
      "cape": 4513,
      "carbohydrate": 4514,
      "carl": 4515,
      "carolina": 4516,
      "catalonia": 4517,
      "cả": 4518,
      "chao": 4519,
      "charlie": 4520,
      "christian": 4521,
      "chuốt": 4522,
      "chát": 4523,
      "chét": 4524,
      "chóc": 4525,
      "chót": 4526,
      "chùng": 4527,
      "chăc": 4528,
      "chơ": 4529,
      "chưng": 4530,
      "chắp": 4531,
      "chọi": 4532,
      "chồi": 4533,
      "chội": 4534,
      "chớm": 4535,
      "chững": 4536,
      "clara": 4537,
      "cleopatra": 4538,
      "club": 4539,
      "coca": 4540,
      "colorado": 4541,
      "coolidge": 4542,
      "cpr": 4543,
      "creep": 4544,
      "cupcake": 4545,
      "cóng": 4546,
      "cù": 4547,
      "căm": 4548,
      "cạp": 4549,
      "cẳng": 4550,
      "cộc": 4551,
      "củng": 4552,
      "dai": 4553,
      "daisuke": 4554,
      "dana": 4555,
      "dance": 4556,
      "daniel": 4557,
      "danube": 4558,
      "darcy": 4559,
      "dau": 4560,
      "dạy": 4561,
      "degas": 4562,
      "delhi": 4563,
      "dennis": 4564,
      "diana": 4565,
      "don": 4566,
      "dones": 4567,
      "dvd": 4568,
      "dùi": 4569,
      "dĩ": 4570,
      "dưng": 4571,
      "dậm": 4572,
      "dẳng": 4573,
      "dẻo": 4574,
      "dề": 4575,
      "ecuador": 4576,
      "edgewise": 4577,
      "eggnog": 4578,
      "elba": 4579,
      "elena": 4580,
      "eliot": 4581,
      "ellen": 4582,
      "enchiladas": 4583,
      "encore": 4584,
      "espresso": 4585,
      "ethiopian": 4586,
      "everett": 4587,
      "f": 4588,
      "faq": 4589,
      "fatima": 4590,
      "fedora": 4591,
      "fi": 4592,
      "finland": 4593,
      "florence": 4594,
      "flunkey": 4595,
      "francine": 4596,
      "françois": 4597,
      "gab": 4598,
      "gaga": 4599,
      "ganpool": 4600,
      "gary": 4601,
      "ghet": 4602,
      "ghẹo": 4603,
      "giận": 4604,
      "giòi": 4605,
      "giấm": 4606,
      "glee": 4607,
      "gnp": 4608,
      "goi": 4609,
      "gps": 4610,
      "greene": 4611,
      "guam": 4612,
      "guitarist": 4613,
      "gulliver": 4614,
      "gáo": 4615,
      "gáy": 4616,
      "gã": 4617,
      "gặp": 4618,
      "gộp": 4619,
      "halley": 4620,
      "hans": 4621,
      "harilyn": 4622,
      "harmonica": 4623,
      "helium": 4624,
      "herbert": 4625,
      "herman": 4626,
      "hikari": 4627,
      "himekusa": 4628,
      "hiroko": 4629,
      "hitler": 4630,
      "hiếp": 4631,
      "hoe": 4632,
      "hoi": 4633,
      "holmes": 4634,
      "honpered": 4635,
      "honshu": 4636,
      "hooky": 4637,
      "horn": 4638,
      "hoshino": 4639,
      "họ": 4640,
      "hums": 4641,
      "huých": 4642,
      "hãm": 4643,
      "hích": 4644,
      "hăm": 4645,
      "hũ": 4646,
      "hấn": 4647,
      "hất": 4648,
      "hằng": 4649,
      "hẻo": 4650,
      "hổi": 4651,
      "hở": 4652,
      "iaido": 4653,
      "ichi": 4654,
      "illinois": 4655,
      "ionescu": 4656,
      "ipod": 4657,
      "irene": 4658,
      "iris": 4659,
      "irs": 4660,
      "isabela": 4661,
      "isopropyl": 4662,
      "israel": 4663,
      "istanbul": 4664,
      "itoh": 4665,
      "izu": 4666,
      "jacob": 4667,
      "jan": 4668,
      "jasmin": 4669,
      "jaywalking": 4670,
      "jeffrey": 4671,
      "jer": 4672,
      "jeremy": 4673,
      "jerry": 4674,
      "jonathan": 4675,
      "juan": 4676,
      "judo": 4677,
      "julius": 4678,
      "kaiser": 4679,
      "kakogawa": 4680,
      "kanguru": 4681,
      "kaori": 4682,
      "karl": 4683,
      "kato": 4684,
      "keller": 4685,
      "kelly": 4686,
      "khoc": 4687,
      "khom": 4688,
      "khoá": 4689,
      "khoả": 4690,
      "khoẻ": 4691,
      "khuếch": 4692,
      "khâm": 4693,
      "khải": 4694,
      "khắt": 4695,
      "khịt": 4696,
      "khống": 4697,
      "koji": 4698,
      "kosher": 4699,
      "kushiro": 4700,
      "ky": 4701,
      "kylie": 4702,
      "kĩ": 4703,
      "kị": 4704,
      "lady": 4705,
      "lanh": 4706,
      "lanka": 4707,
      "layover": 4708,
      "lại": 4709,
      "lem": 4710,
      "leonardo": 4711,
      "liliuokalani": 4712,
      "limousine": 4713,
      "linux": 4714,
      "lisbon": 4715,
      "liz": 4716,
      "liêng": 4717,
      "llama": 4718,
      "louie": 4719,
      "louisiana": 4720,
      "loét": 4721,
      "ltd": 4722,
      "luồn": 4723,
      "lâm": 4724,
      "lâng": 4725,
      "lí": 4726,
      "líu": 4727,
      "lòa": 4728,
      "lóa": 4729,
      "lóng": 4730,
      "lõm": 4731,
      "lúp": 4732,
      "lơi": 4733,
      "lư": 4734,
      "lấn": 4735,
      "lọi": 4736,
      "lọn": 4737,
      "lụi": 4738,
      "lự": 4739,
      "mafia": 4740,
      "marcia": 4741,
      "mark": 4742,
      "marketing": 4743,
      "martini": 4744,
      "masao": 4745,
      "masha": 4746,
      "mau": 4747,
      "max": 4748,
      "mcclellan": 4749,
      "meds": 4750,
      "meiji": 4751,
      "melville": 4752,
      "mercedes": 4753,
      "mẹ": 4754,
      "mini": 4755,
      "minogue": 4756,
      "miyuki": 4757,
      "mohammed": 4758,
      "moi": 4759,
      "mona": 4760,
      "mot": 4761,
      "mrs": 4762,
      "muffin": 4763,
      "mulligan": 4764,
      "murata": 4765,
      "muồi": 4766,
      "mật": 4767,
      "mía": 4768,
      "mông": 4769,
      "múi": 4770,
      "măn": 4771,
      "mạp": 4772,
      "mấu": 4773,
      "mẩn": 4774,
      "mỉ": 4775,
      "mụ": 4776,
      "mủi": 4777,
      "mửa": 4778,
      "n": 4779,
      "nakamura": 4780,
      "nakano": 4781,
      "nang": 4782,
      "napoleon": 4783,
      "nasa": 4784,
      "ned": 4785,
      "nepal": 4786,
      "neptune": 4787,
      "neruda": 4788,
      "ngạc": 4789,
      "ngủ": 4790,
      "ngái": 4791,
      "ngòi": 4792,
      "ngõ": 4793,
      "ngăm": 4794,
      "nhat": 4795,
      "nhi": 4796,
      "nhin": 4797,
      "nhk": 4798,
      "nhoài": 4799,
      "nhung": 4800,
      "nhám": 4801,
      "nhún": 4802,
      "nhướng": 4803,
      "nhầy": 4804,
      "nhẽo": 4805,
      "nhếch": 4806,
      "nightingale": 4807,
      "niken": 4808,
      "nikkei": 4809,
      "nile": 4810,
      "nintendo": 4811,
      "noah": 4812,
      "nomo": 4813,
      "noriko": 4814,
      "notepad": 4815,
      "nozomi": 4816,
      "ntt": 4817,
      "nuối": 4818,
      "nài": 4819,
      "nành": 4820,
      "nách": 4821,
      "nán": 4822,
      "náo": 4823,
      "nêm": 4824,
      "nón": 4825,
      "nấp": 4826,
      "nẹp": 4827,
      "nộm": 4828,
      "obihiro": 4829,
      "ogaki": 4830,
      "okayama": 4831,
      "oklahoma": 4832,
      "okonomiyaki": 4833,
      "oleg": 4834,
      "ophelia": 4835,
      "orleans": 4836,
      "orville": 4837,
      "oslo": 4838,
      "ozone": 4839,
      "oải": 4840,
      "pansies": 4841,
      "patty": 4842,
      "philippines": 4843,
      "photocopy": 4844,
      "phuc": 4845,
      "phường": 4846,
      "phế": 4847,
      "phết": 4848,
      "pizzaro": 4849,
      "pko": 4850,
      "playstation": 4851,
      "plutonium": 4852,
      "podcast": 4853,
      "polk": 4854,
      "popeye": 4855,
      "portband": 4856,
      "poster": 4857,
      "potter": 4858,
      "poyang": 4859,
      "putt": 4860,
      "pô": 4861,
      "quaker": 4862,
      "quebec": 4863,
      "quyển": 4864,
      "quại": 4865,
      "quằn": 4866,
      "quẹo": 4867,
      "quẹt": 4868,
      "ram": 4869,
      "ramu": 4870,
      "rang": 4871,
      "reggae": 4872,
      "rembrandt": 4873,
      "rev": 4874,
      "rick": 4875,
      "roll": 4876,
      "ron": 4877,
      "root": 4878,
      "rum": 4879,
      "ráo": 4880,
      "rát": 4881,
      "rã": 4882,
      "rét": 4883,
      "ròng": 4884,
      "rông": 4885,
      "răn": 4886,
      "rước": 4887,
      "rạch": 4888,
      "rầy": 4889,
      "rộp": 4890,
      "rữa": 4891,
      "saddam": 4892,
      "salsa": 4893,
      "saturn": 4894,
      "seiko": 4895,
      "sharon": 4896,
      "shiitake": 4897,
      "shintaro": 4898,
      "shogi": 4899,
      "show": 4900,
      "sioux": 4901,
      "sirhan": 4902,
      "sistine": 4903,
      "smack": 4904,
      "snap": 4905,
      "socrates": 4906,
      "solitaire": 4907,
      "solo": 4908,
      "sonnet": 4909,
      "soạng": 4910,
      "spielberg": 4911,
      "sterling": 4912,
      "steroid": 4913,
      "stradivarius": 4914,
      "studio": 4915,
      "sundae": 4916,
      "suv": 4917,
      "suzanne": 4918,
      "swing": 4919,
      "sôcôla": 4920,
      "sùi": 4921,
      "sải": 4922,
      "sầu": 4923,
      "sờn": 4924,
      "sứa": 4925,
      "sứt": 4926,
      "sỹ": 4927,
      "takako": 4928,
      "takuboku": 4929,
      "tasmania": 4930,
      "the": 4931,
      "theodore": 4932,
      "thiếc": 4933,
      "thoa": 4934,
      "thoạt": 4935,
      "thoả": 4936,
      "thẳng": 4937,
      "thưc": 4938,
      "thử": 4939,
      "thềm": 4940,
      "thỏi": 4941,
      "thớt": 4942,
      "thụy": 4943,
      "tiki": 4944,
      "toefl": 4945,
      "tokaido": 4946,
      "toronto": 4947,
      "toshio": 4948,
      "trả": 4949,
      "trifled": 4950,
      "troulette": 4951,
      "trám": 4952,
      "trắc": 4953,
      "trặc": 4954,
      "trụy": 4955,
      "tux": 4956,
      "tuôn": 4957,
      "tuếch": 4958,
      "tuỳ": 4959,
      "tà": 4960,
      "té": 4961,
      "tôt": 4962,
      "tơi": 4963,
      "tể": 4964,
      "tỉ": 4965,
      "tụy": 4966,
      "ua": 4967,
      "udon": 4968,
      "ufos": 4969,
      "un": 4970,
      "unesco": 4971,
      "uyển": 4972,
      "uất": 4973,
      "vao": 4974,
      "vegas": 4975,
      "vinci": 4976,
      "vip": 4977,
      "virginia": 4978,
      "von": 4979,
      "vọng": 4980,
      "vw": 4981,
      "vãn": 4982,
      "vôi": 4983,
      "võng": 4984,
      "vấy": 4985,
      "vầng": 4986,
      "w": 4987,
      "watanabe": 4988,
      "webb": 4989,
      "wi": 4990,
      "wikipedia": 4991,
      "xảy": 4992,
      "xoài": 4993,
      "xào": 4994,
      "xén": 4995,
      "xõa": 4996,
      "xù": 4997,
      "xơ": 4998,
      "xướng": 4999,
      "xắc": 5000,
      "xỉa": 5001,
      "xối": 5002,
      "xới": 5003,
      "yaesu": 5004,
      "yoshida": 5005,
      "yoshio": 5006,
      "yuriko": 5007,
      "zao": 5008,
      "°": 5009,
      "Ít": 5010,
      "ôi": 5011,
      "Đan": 5012,
      "Đài": 5013,
      "Đâu": 5014,
      "Đảng": 5015,
      "Đống": 5016,
      "Đồ": 5017,
      "Đổ": 5018,
      "điềm": 5019,
      "đu": 5020,
      "đuốc": 5021,
      "để": 5022,
      "đìa": 5023,
      "đơi": 5024,
      "đềm": 5025,
      "ạ": 5026,
      "ị": 5027,
      "ối": 5028
    },
    "unk_token": "[UNK]"
  }
}